{
  "mapTransformer": {
    "0": [
      "aload_0",
      1,
      1
    ],
    "1": [
      "ifnonnull",
      1,
      1
    ],
    "2": [
      "7",
      1,
      1
    ],
    "4": [
      "invokestatic",
      1,
      0
    ],
    "5": [
      "org/apache/commons/collections4/functors/ConstantTransformer.nullTransformer:()Lorg/apache/commons/collections4/Transformer;",
      1,
      0
    ],
    "7": [
      "areturn",
      1,
      0
    ],
    "8": [
      "new",
      0,
      0
    ],
    "9": [
      "org/apache/commons/collections4/functors/MapTransformer",
      0,
      0
    ],
    "11": [
      "dup",
      0,
      0
    ],
    "12": [
      "aload_0",
      0,
      0
    ],
    "13": [
      "invokespecial",
      0,
      0
    ],
    "14": [
      "org/apache/commons/collections4/functors/MapTransformer.<init>:(Ljava/util/Map;)V",
      0,
      0
    ],
    "16": [
      "areturn",
      0,
      0
    ]
  },
  "<init>": {
    "0": [
      "aload_0",
      0,
      0
    ],
    "1": [
      "invokespecial",
      0,
      0
    ],
    "2": [
      "java/lang/Object.<init>:()V",
      0,
      0
    ],
    "4": [
      "aload_0",
      0,
      0
    ],
    "5": [
      "aload_1",
      0,
      0
    ],
    "6": [
      "putfield",
      0,
      0
    ],
    "7": [
      "org/apache/commons/collections4/functors/MapTransformer.iMap:Ljava/util/Map;",
      0,
      0
    ],
    "9": [
      "return",
      0,
      0
    ]
  },
  "transform": {
    "0": [
      "aload_0",
      0,
      0
    ],
    "1": [
      "getfield",
      0,
      0
    ],
    "2": [
      "org/apache/commons/collections4/functors/MapTransformer.iMap:Ljava/util/Map;",
      0,
      0
    ],
    "4": [
      "aload_1",
      0,
      0
    ],
    "5": [
      "invokeinterface",
      0,
      0
    ],
    "6": [
      "java/util/Map.java/lang/Object",
      0,
      0
    ],
    "8": [
      "0",
      0,
      0
    ],
    "10": [
      "areturn",
      0,
      0
    ]
  },
  "getMap": {
    "0": [
      "aload_0",
      0,
      0
    ],
    "1": [
      "getfield",
      0,
      0
    ],
    "2": [
      "org/apache/commons/collections4/functors/MapTransformer.iMap:Ljava/util/Map;",
      0,
      0
    ],
    "4": [
      "areturn",
      0,
      0
    ]
  }
}