{
  "<init>": {
    "0": [
      "aload_0",
      0,
      0
    ],
    "1": [
      "invokespecial",
      0,
      0
    ],
    "2": [
      "java/lang/Object.<init>:()V",
      0,
      0
    ],
    "4": [
      "aload_0",
      0,
      0
    ],
    "5": [
      "aload_0",
      0,
      0
    ],
    "6": [
      "aload_1",
      0,
      0
    ],
    "7": [
      "invokevirtual",
      0,
      0
    ],
    "8": [
      "org/apache/commons/math3/stat/correlation/KendallsCorrelation.computeCorrelationMatrix:(Lorg/apache/commons/math3/linear/RealMatrix;)Lorg/apache/commons/math3/linear/RealMatrix;",
      0,
      0
    ],
    "10": [
      "putfield",
      0,
      0
    ],
    "11": [
      "org/apache/commons/math3/stat/correlation/KendallsCorrelation.correlationMatrix:Lorg/apache/commons/math3/linear/RealMatrix;",
      0,
      0
    ],
    "13": [
      "return",
      0,
      0
    ]
  },
  "getCorrelationMatrix": {
    "0": [
      "aload_0",
      0,
      0
    ],
    "1": [
      "getfield",
      0,
      0
    ],
    "2": [
      "org/apache/commons/math3/stat/correlation/KendallsCorrelation.correlationMatrix:Lorg/apache/commons/math3/linear/RealMatrix;",
      0,
      0
    ],
    "4": [
      "areturn",
      0,
      0
    ]
  },
  "computeCorrelationMatrix": {
    "0": [
      "aload_0",
      0,
      0
    ],
    "1": [
      "new",
      0,
      0
    ],
    "2": [
      "org/apache/commons/math3/linear/BlockRealMatrix",
      0,
      0
    ],
    "4": [
      "dup",
      0,
      0
    ],
    "5": [
      "aload_1",
      0,
      0
    ],
    "6": [
      "invokespecial",
      0,
      0
    ],
    "7": [
      "org/apache/commons/math3/linear/BlockRealMatrix.<init>:([[D)V",
      0,
      0
    ],
    "9": [
      "invokevirtual",
      0,
      0
    ],
    "10": [
      "org/apache/commons/math3/stat/correlation/KendallsCorrelation.computeCorrelationMatrix:(Lorg/apache/commons/math3/linear/RealMatrix;)Lorg/apache/commons/math3/linear/RealMatrix;",
      0,
      0
    ],
    "12": [
      "areturn",
      0,
      0
    ]
  },
  "correlation": {
    "0": [
      "aload_1",
      1,
      1
    ],
    "1": [
      "arraylength",
      1,
      1
    ],
    "2": [
      "aload_2",
      1,
      1
    ],
    "3": [
      "arraylength",
      1,
      1
    ],
    "4": [
      "if_icmpeq",
      1,
      1
    ],
    "5": [
      "15",
      1,
      1
    ],
    "7": [
      "new",
      1,
      0
    ],
    "8": [
      "org/apache/commons/math3/exception/DimensionMismatchException",
      1,
      0
    ],
    "10": [
      "dup",
      1,
      0
    ],
    "11": [
      "aload_1",
      1,
      0
    ],
    "12": [
      "arraylength",
      1,
      0
    ],
    "13": [
      "aload_2",
      1,
      0
    ],
    "14": [
      "arraylength",
      1,
      0
    ],
    "15": [
      "invokespecial",
      1,
      0
    ],
    "16": [
      "org/apache/commons/math3/exception/DimensionMismatchException.<init>:(II)V",
      1,
      0
    ],
    "18": [
      "athrow",
      1,
      0
    ],
    "19": [
      "aload_1",
      0,
      0
    ],
    "20": [
      "arraylength",
      0,
      0
    ],
    "21": [
      "istore_3",
      0,
      0
    ],
    "22": [
      "iload_3",
      0,
      0
    ],
    "23": [
      "iconst_1",
      0,
      0
    ],
    "24": [
      "isub",
      0,
      0
    ],
    "25": [
      "i2l",
      0,
      0
    ],
    "26": [
      "invokestatic",
      0,
      0
    ],
    "27": [
      "org/apache/commons/math3/stat/correlation/KendallsCorrelation.sum:(J)J",
      0,
      0
    ],
    "29": [
      "lstore",
      0,
      0
    ],
    "30": [
      "#4",
      0,
      0
    ],
    "31": [
      "iload_3",
      0,
      0
    ],
    "32": [
      "anewarray",
      0,
      0
    ],
    "33": [
      "org/apache/commons/math3/util/Pair",
      0,
      0
    ],
    "35": [
      "astore",
      0,
      0
    ],
    "36": [
      "#6",
      0,
      0
    ],
    "37": [
      "iconst_0",
      1,
      4
    ],
    "38": [
      "istore",
      1,
      4
    ],
    "39": [
      "#7",
      1,
      4
    ],
    "40": [
      "iload",
      1,
      4
    ],
    "41": [
      "#7",
      1,
      4
    ],
    "42": [
      "iload_3",
      1,
      4
    ],
    "43": [
      "if_icmpge",
      1,
      4
    ],
    "44": [
      "35",
      1,
      4
    ],
    "46": [
      "aload",
      1,
      0
    ],
    "47": [
      "#6",
      1,
      0
    ],
    "48": [
      "iload",
      1,
      0
    ],
    "49": [
      "#7",
      1,
      0
    ],
    "50": [
      "new",
      1,
      0
    ],
    "51": [
      "org/apache/commons/math3/util/Pair",
      1,
      0
    ],
    "53": [
      "dup",
      1,
      0
    ],
    "54": [
      "aload_1",
      1,
      0
    ],
    "55": [
      "iload",
      1,
      0
    ],
    "56": [
      "#7",
      1,
      0
    ],
    "57": [
      "daload",
      1,
      0
    ],
    "58": [
      "invokestatic",
      1,
      0
    ],
    "59": [
      "java/lang/Double.valueOf:(D)Ljava/lang/Double;",
      1,
      0
    ],
    "61": [
      "aload_2",
      1,
      0
    ],
    "62": [
      "iload",
      1,
      0
    ],
    "63": [
      "#7",
      1,
      0
    ],
    "64": [
      "daload",
      1,
      0
    ],
    "65": [
      "invokestatic",
      1,
      0
    ],
    "66": [
      "java/lang/Double.valueOf:(D)Ljava/lang/Double;",
      1,
      0
    ],
    "68": [
      "invokespecial",
      1,
      0
    ],
    "69": [
      "org/apache/commons/math3/util/Pair.<init>:(Ljava/lang/Object;Ljava/lang/Object;)V",
      1,
      0
    ],
    "71": [
      "aastore",
      1,
      0
    ],
    "72": [
      "iinc",
      1,
      0
    ],
    "73": [
      "#7",
      1,
      0
    ],
    "74": [
      "-89",
      1,
      0
    ],
    "75": [
      "goto",
      1,
      4
    ],
    "76": [
      "-35",
      1,
      4
    ],
    "78": [
      "aload",
      0,
      0
    ],
    "79": [
      "#6",
      0,
      0
    ],
    "80": [
      "new",
      0,
      0
    ],
    "81": [
      "org/apache/commons/math3/stat/correlation/KendallsCorrelation$1",
      0,
      0
    ],
    "83": [
      "dup",
      0,
      0
    ],
    "84": [
      "aload_0",
      0,
      0
    ],
    "85": [
      "invokespecial",
      0,
      0
    ],
    "86": [
      "org/apache/commons/math3/stat/correlation/KendallsCorrelation$1.<init>:(Lorg/apache/commons/math3/stat/correlation/KendallsCorrelation;)V",
      0,
      0
    ],
    "88": [
      "invokestatic",
      0,
      0
    ],
    "89": [
      "java/util/Arrays.sort:([Ljava/lang/Object;Ljava/util/Comparator;)V",
      0,
      0
    ],
    "91": [
      "lconst_0",
      0,
      0
    ],
    "92": [
      "lstore",
      0,
      0
    ],
    "93": [
      "#7",
      0,
      0
    ],
    "94": [
      "lconst_0",
      0,
      0
    ],
    "95": [
      "lstore",
      0,
      0
    ],
    "96": [
      "#9",
      0,
      0
    ],
    "97": [
      "lconst_1",
      0,
      0
    ],
    "98": [
      "lstore",
      0,
      0
    ],
    "99": [
      "#11",
      0,
      0
    ],
    "100": [
      "lconst_1",
      0,
      0
    ],
    "101": [
      "lstore",
      0,
      0
    ],
    "102": [
      "#13",
      0,
      0
    ],
    "103": [
      "aload",
      0,
      0
    ],
    "104": [
      "#6",
      0,
      0
    ],
    "105": [
      "iconst_0",
      0,
      0
    ],
    "106": [
      "aaload",
      0,
      0
    ],
    "107": [
      "astore",
      0,
      0
    ],
    "108": [
      "#15",
      0,
      0
    ],
    "109": [
      "iconst_1",
      1,
      4
    ],
    "110": [
      "istore",
      1,
      4
    ],
    "111": [
      "#16",
      1,
      4
    ],
    "112": [
      "iload",
      1,
      4
    ],
    "113": [
      "#16",
      1,
      4
    ],
    "114": [
      "iload_3",
      1,
      4
    ],
    "115": [
      "if_icmpge",
      1,
      4
    ],
    "116": [
      "121",
      1,
      4
    ],
    "118": [
      "aload",
      1,
      0
    ],
    "119": [
      "#6",
      1,
      0
    ],
    "120": [
      "iload",
      1,
      0
    ],
    "121": [
      "#16",
      1,
      0
    ],
    "122": [
      "aaload",
      1,
      0
    ],
    "123": [
      "astore",
      1,
      0
    ],
    "124": [
      "#17",
      1,
      0
    ],
    "125": [
      "aload",
      2,
      1
    ],
    "126": [
      "#17",
      2,
      1
    ],
    "127": [
      "invokevirtual",
      2,
      1
    ],
    "128": [
      "org/apache/commons/math3/util/Pair.getFirst:()Ljava/lang/Object;",
      2,
      1
    ],
    "130": [
      "checkcast",
      2,
      1
    ],
    "131": [
      "java/lang/Double",
      2,
      1
    ],
    "133": [
      "aload",
      2,
      1
    ],
    "134": [
      "#15",
      2,
      1
    ],
    "135": [
      "invokevirtual",
      2,
      1
    ],
    "136": [
      "org/apache/commons/math3/util/Pair.getFirst:()Ljava/lang/Object;",
      2,
      1
    ],
    "138": [
      "invokevirtual",
      2,
      1
    ],
    "139": [
      "java/lang/Double.equals:(Ljava/lang/Object;)Z",
      2,
      1
    ],
    "141": [
      "ifeq",
      2,
      1
    ],
    "142": [
      "55",
      2,
      1
    ],
    "144": [
      "lload",
      2,
      0
    ],
    "145": [
      "#11",
      2,
      0
    ],
    "146": [
      "lconst_1",
      2,
      0
    ],
    "147": [
      "ladd",
      2,
      0
    ],
    "148": [
      "lstore",
      2,
      0
    ],
    "149": [
      "#11",
      2,
      0
    ],
    "150": [
      "aload",
      3,
      1
    ],
    "151": [
      "#17",
      3,
      1
    ],
    "152": [
      "invokevirtual",
      3,
      1
    ],
    "153": [
      "org/apache/commons/math3/util/Pair.getSecond:()Ljava/lang/Object;",
      3,
      1
    ],
    "155": [
      "checkcast",
      3,
      1
    ],
    "156": [
      "java/lang/Double",
      3,
      1
    ],
    "158": [
      "aload",
      3,
      1
    ],
    "159": [
      "#15",
      3,
      1
    ],
    "160": [
      "invokevirtual",
      3,
      1
    ],
    "161": [
      "org/apache/commons/math3/util/Pair.getSecond:()Ljava/lang/Object;",
      3,
      1
    ],
    "163": [
      "invokevirtual",
      3,
      1
    ],
    "164": [
      "java/lang/Double.equals:(Ljava/lang/Object;)Z",
      3,
      1
    ],
    "166": [
      "ifeq",
      3,
      1
    ],
    "167": [
      "12",
      3,
      1
    ],
    "169": [
      "lload",
      3,
      0
    ],
    "170": [
      "#13",
      3,
      0
    ],
    "171": [
      "lconst_1",
      3,
      0
    ],
    "172": [
      "ladd",
      3,
      0
    ],
    "173": [
      "lstore",
      3,
      0
    ],
    "174": [
      "#13",
      3,
      0
    ],
    "175": [
      "goto",
      3,
      0
    ],
    "176": [
      "51",
      3,
      0
    ],
    "178": [
      "lload",
      3,
      0
    ],
    "179": [
      "#9",
      3,
      0
    ],
    "180": [
      "lload",
      3,
      0
    ],
    "181": [
      "#13",
      3,
      0
    ],
    "182": [
      "lconst_1",
      3,
      0
    ],
    "183": [
      "lsub",
      3,
      0
    ],
    "184": [
      "invokestatic",
      3,
      0
    ],
    "185": [
      "org/apache/commons/math3/stat/correlation/KendallsCorrelation.sum:(J)J",
      3,
      0
    ],
    "187": [
      "ladd",
      3,
      0
    ],
    "188": [
      "lstore",
      3,
      0
    ],
    "189": [
      "#9",
      3,
      0
    ],
    "190": [
      "lconst_1",
      3,
      0
    ],
    "191": [
      "lstore",
      3,
      0
    ],
    "192": [
      "#13",
      3,
      0
    ],
    "193": [
      "goto",
      3,
      0
    ],
    "194": [
      "33",
      3,
      0
    ],
    "196": [
      "lload",
      2,
      0
    ],
    "197": [
      "#7",
      2,
      0
    ],
    "198": [
      "lload",
      2,
      0
    ],
    "199": [
      "#11",
      2,
      0
    ],
    "200": [
      "lconst_1",
      2,
      0
    ],
    "201": [
      "lsub",
      2,
      0
    ],
    "202": [
      "invokestatic",
      2,
      0
    ],
    "203": [
      "org/apache/commons/math3/stat/correlation/KendallsCorrelation.sum:(J)J",
      2,
      0
    ],
    "205": [
      "ladd",
      2,
      0
    ],
    "206": [
      "lstore",
      2,
      0
    ],
    "207": [
      "#7",
      2,
      0
    ],
    "208": [
      "lconst_1",
      2,
      0
    ],
    "209": [
      "lstore",
      2,
      0
    ],
    "210": [
      "#11",
      2,
      0
    ],
    "211": [
      "lload",
      2,
      0
    ],
    "212": [
      "#9",
      2,
      0
    ],
    "213": [
      "lload",
      2,
      0
    ],
    "214": [
      "#13",
      2,
      0
    ],
    "215": [
      "lconst_1",
      2,
      0
    ],
    "216": [
      "lsub",
      2,
      0
    ],
    "217": [
      "invokestatic",
      2,
      0
    ],
    "218": [
      "org/apache/commons/math3/stat/correlation/KendallsCorrelation.sum:(J)J",
      2,
      0
    ],
    "220": [
      "ladd",
      2,
      0
    ],
    "221": [
      "lstore",
      2,
      0
    ],
    "222": [
      "#9",
      2,
      0
    ],
    "223": [
      "lconst_1",
      2,
      0
    ],
    "224": [
      "lstore",
      2,
      0
    ],
    "225": [
      "#13",
      2,
      0
    ],
    "226": [
      "aload",
      1,
      0
    ],
    "227": [
      "#17",
      1,
      0
    ],
    "228": [
      "astore",
      1,
      0
    ],
    "229": [
      "#15",
      1,
      0
    ],
    "230": [
      "iinc",
      1,
      0
    ],
    "231": [
      "#16",
      1,
      0
    ],
    "232": [
      "-89",
      1,
      0
    ],
    "233": [
      "goto",
      1,
      4
    ],
    "234": [
      "-121",
      1,
      4
    ],
    "236": [
      "lload",
      0,
      0
    ],
    "237": [
      "#7",
      0,
      0
    ],
    "238": [
      "lload",
      0,
      0
    ],
    "239": [
      "#11",
      0,
      0
    ],
    "240": [
      "lconst_1",
      0,
      0
    ],
    "241": [
      "lsub",
      0,
      0
    ],
    "242": [
      "invokestatic",
      0,
      0
    ],
    "243": [
      "org/apache/commons/math3/stat/correlation/KendallsCorrelation.sum:(J)J",
      0,
      0
    ],
    "245": [
      "ladd",
      0,
      0
    ],
    "246": [
      "lstore",
      0,
      0
    ],
    "247": [
      "#7",
      0,
      0
    ],
    "248": [
      "lload",
      0,
      0
    ],
    "249": [
      "#9",
      0,
      0
    ],
    "250": [
      "lload",
      0,
      0
    ],
    "251": [
      "#13",
      0,
      0
    ],
    "252": [
      "lconst_1",
      0,
      0
    ],
    "253": [
      "lsub",
      0,
      0
    ],
    "254": [
      "invokestatic",
      0,
      0
    ],
    "255": [
      "org/apache/commons/math3/stat/correlation/KendallsCorrelation.sum:(J)J",
      0,
      0
    ],
    "257": [
      "ladd",
      0,
      0
    ],
    "258": [
      "lstore",
      0,
      0
    ],
    "259": [
      "#9",
      0,
      0
    ],
    "260": [
      "lconst_0",
      0,
      0
    ],
    "261": [
      "lstore",
      0,
      0
    ],
    "262": [
      "#16",
      0,
      0
    ],
    "263": [
      "iload_3",
      0,
      0
    ],
    "264": [
      "anewarray",
      0,
      0
    ],
    "265": [
      "org/apache/commons/math3/util/Pair",
      0,
      0
    ],
    "267": [
      "astore",
      0,
      0
    ],
    "268": [
      "#18",
      0,
      0
    ],
    "269": [
      "iconst_1",
      1,
      4
    ],
    "270": [
      "istore",
      1,
      4
    ],
    "271": [
      "#19",
      1,
      4
    ],
    "272": [
      "iload",
      1,
      4
    ],
    "273": [
      "#19",
      1,
      4
    ],
    "274": [
      "iload_3",
      1,
      4
    ],
    "275": [
      "if_icmpge",
      1,
      4
    ],
    "276": [
      "213",
      1,
      4
    ],
    "278": [
      "iconst_0",
      2,
      4
    ],
    "279": [
      "istore",
      2,
      4
    ],
    "280": [
      "#20",
      2,
      4
    ],
    "281": [
      "iload",
      2,
      4
    ],
    "282": [
      "#20",
      2,
      4
    ],
    "283": [
      "iload_3",
      2,
      4
    ],
    "284": [
      "if_icmpge",
      2,
      4
    ],
    "285": [
      "183",
      2,
      4
    ],
    "287": [
      "iload",
      2,
      0
    ],
    "288": [
      "#20",
      2,
      0
    ],
    "289": [
      "istore",
      2,
      0
    ],
    "290": [
      "#21",
      2,
      0
    ],
    "291": [
      "iload",
      2,
      0
    ],
    "292": [
      "#21",
      2,
      0
    ],
    "293": [
      "iload",
      2,
      0
    ],
    "294": [
      "#19",
      2,
      0
    ],
    "295": [
      "iadd",
      2,
      0
    ],
    "296": [
      "iload_3",
      2,
      0
    ],
    "297": [
      "invokestatic",
      2,
      0
    ],
    "298": [
      "org/apache/commons/math3/util/FastMath.min:(II)I",
      2,
      0
    ],
    "300": [
      "istore",
      2,
      0
    ],
    "301": [
      "#22",
      2,
      0
    ],
    "302": [
      "iload",
      2,
      0
    ],
    "303": [
      "#22",
      2,
      0
    ],
    "304": [
      "istore",
      2,
      0
    ],
    "305": [
      "#23",
      2,
      0
    ],
    "306": [
      "iload",
      2,
      0
    ],
    "307": [
      "#23",
      2,
      0
    ],
    "308": [
      "iload",
      2,
      0
    ],
    "309": [
      "#19",
      2,
      0
    ],
    "310": [
      "iadd",
      2,
      0
    ],
    "311": [
      "iload_3",
      2,
      0
    ],
    "312": [
      "invokestatic",
      2,
      0
    ],
    "313": [
      "org/apache/commons/math3/util/FastMath.min:(II)I",
      2,
      0
    ],
    "315": [
      "istore",
      2,
      0
    ],
    "316": [
      "#24",
      2,
      0
    ],
    "317": [
      "iload",
      2,
      0
    ],
    "318": [
      "#20",
      2,
      0
    ],
    "319": [
      "istore",
      2,
      0
    ],
    "320": [
      "#25",
      2,
      0
    ],
    "321": [
      "iload",
      3,
      3
    ],
    "322": [
      "#21",
      3,
      3
    ],
    "323": [
      "iload",
      3,
      3
    ],
    "324": [
      "#22",
      3,
      3
    ],
    "325": [
      "if_icmplt",
      3,
      3
    ],
    "326": [
      "10",
      3,
      3
    ],
    "328": [
      "iload",
      3,
      3
    ],
    "329": [
      "#23",
      3,
      3
    ],
    "330": [
      "iload",
      3,
      3
    ],
    "331": [
      "#24",
      3,
      3
    ],
    "332": [
      "if_icmpge",
      3,
      3
    ],
    "333": [
      "123",
      3,
      3
    ],
    "335": [
      "iload",
      4,
      1
    ],
    "336": [
      "#21",
      4,
      1
    ],
    "337": [
      "iload",
      4,
      1
    ],
    "338": [
      "#22",
      4,
      1
    ],
    "339": [
      "if_icmpge",
      4,
      1
    ],
    "340": [
      "97",
      4,
      1
    ],
    "342": [
      "iload",
      5,
      1
    ],
    "343": [
      "#23",
      5,
      1
    ],
    "344": [
      "iload",
      5,
      1
    ],
    "345": [
      "#24",
      5,
      1
    ],
    "346": [
      "if_icmpge",
      5,
      1
    ],
    "347": [
      "74",
      5,
      1
    ],
    "349": [
      "aload",
      6,
      1
    ],
    "350": [
      "#6",
      6,
      1
    ],
    "351": [
      "iload",
      6,
      1
    ],
    "352": [
      "#21",
      6,
      1
    ],
    "353": [
      "aaload",
      6,
      1
    ],
    "354": [
      "invokevirtual",
      6,
      1
    ],
    "355": [
      "org/apache/commons/math3/util/Pair.getSecond:()Ljava/lang/Object;",
      6,
      1
    ],
    "357": [
      "checkcast",
      6,
      1
    ],
    "358": [
      "java/lang/Double",
      6,
      1
    ],
    "360": [
      "aload",
      6,
      1
    ],
    "361": [
      "#6",
      6,
      1
    ],
    "362": [
      "iload",
      6,
      1
    ],
    "363": [
      "#23",
      6,
      1
    ],
    "364": [
      "aaload",
      6,
      1
    ],
    "365": [
      "invokevirtual",
      6,
      1
    ],
    "366": [
      "org/apache/commons/math3/util/Pair.getSecond:()Ljava/lang/Object;",
      6,
      1
    ],
    "368": [
      "checkcast",
      6,
      1
    ],
    "369": [
      "java/lang/Double",
      6,
      1
    ],
    "371": [
      "invokevirtual",
      6,
      1
    ],
    "372": [
      "java/lang/Double.compareTo:(Ljava/lang/Double;)I",
      6,
      1
    ],
    "374": [
      "ifgt",
      6,
      1
    ],
    "375": [
      "19",
      6,
      1
    ],
    "377": [
      "aload",
      6,
      0
    ],
    "378": [
      "#18",
      6,
      0
    ],
    "379": [
      "iload",
      6,
      0
    ],
    "380": [
      "#25",
      6,
      0
    ],
    "381": [
      "aload",
      6,
      0
    ],
    "382": [
      "#6",
      6,
      0
    ],
    "383": [
      "iload",
      6,
      0
    ],
    "384": [
      "#21",
      6,
      0
    ],
    "385": [
      "aaload",
      6,
      0
    ],
    "386": [
      "aastore",
      6,
      0
    ],
    "387": [
      "iinc",
      6,
      0
    ],
    "388": [
      "#21",
      6,
      0
    ],
    "389": [
      "-89",
      6,
      0
    ],
    "390": [
      "goto",
      6,
      0
    ],
    "391": [
      "59",
      6,
      0
    ],
    "393": [
      "aload",
      6,
      0
    ],
    "394": [
      "#18",
      6,
      0
    ],
    "395": [
      "iload",
      6,
      0
    ],
    "396": [
      "#25",
      6,
      0
    ],
    "397": [
      "aload",
      6,
      0
    ],
    "398": [
      "#6",
      6,
      0
    ],
    "399": [
      "iload",
      6,
      0
    ],
    "400": [
      "#23",
      6,
      0
    ],
    "401": [
      "aaload",
      6,
      0
    ],
    "402": [
      "aastore",
      6,
      0
    ],
    "403": [
      "iinc",
      6,
      0
    ],
    "404": [
      "#23",
      6,
      0
    ],
    "405": [
      "22",
      6,
      0
    ],
    "406": [
      "lload",
      6,
      0
    ],
    "407": [
      "#16",
      6,
      0
    ],
    "408": [
      "iload",
      6,
      0
    ],
    "409": [
      "#22",
      6,
      0
    ],
    "410": [
      "iload",
      6,
      0
    ],
    "411": [
      "#21",
      6,
      0
    ],
    "412": [
      "isub",
      6,
      0
    ],
    "413": [
      "i2l",
      6,
      0
    ],
    "414": [
      "ladd",
      6,
      0
    ],
    "415": [
      "lstore",
      6,
      0
    ],
    "416": [
      "#16",
      6,
      0
    ],
    "417": [
      "goto",
      6,
      0
    ],
    "418": [
      "32",
      6,
      0
    ],
    "420": [
      "aload",
      5,
      0
    ],
    "421": [
      "#18",
      5,
      0
    ],
    "422": [
      "iload",
      5,
      0
    ],
    "423": [
      "#25",
      5,
      0
    ],
    "424": [
      "aload",
      5,
      0
    ],
    "425": [
      "#6",
      5,
      0
    ],
    "426": [
      "iload",
      5,
      0
    ],
    "427": [
      "#21",
      5,
      0
    ],
    "428": [
      "aaload",
      5,
      0
    ],
    "429": [
      "aastore",
      5,
      0
    ],
    "430": [
      "iinc",
      5,
      0
    ],
    "431": [
      "#21",
      5,
      0
    ],
    "432": [
      "-89",
      5,
      0
    ],
    "433": [
      "goto",
      5,
      0
    ],
    "434": [
      "16",
      5,
      0
    ],
    "436": [
      "aload",
      4,
      0
    ],
    "437": [
      "#18",
      4,
      0
    ],
    "438": [
      "iload",
      4,
      0
    ],
    "439": [
      "#25",
      4,
      0
    ],
    "440": [
      "aload",
      4,
      0
    ],
    "441": [
      "#6",
      4,
      0
    ],
    "442": [
      "iload",
      4,
      0
    ],
    "443": [
      "#23",
      4,
      0
    ],
    "444": [
      "aaload",
      4,
      0
    ],
    "445": [
      "aastore",
      4,
      0
    ],
    "446": [
      "iinc",
      4,
      0
    ],
    "447": [
      "#23",
      4,
      0
    ],
    "448": [
      "-124",
      4,
      0
    ],
    "449": [
      "iinc",
      3,
      0
    ],
    "450": [
      "#25",
      3,
      0
    ],
    "451": [
      "-89",
      3,
      0
    ],
    "452": [
      "goto",
      3,
      3
    ],
    "453": [
      "-131",
      3,
      3
    ],
    "455": [
      "iload",
      3,
      0
    ],
    "456": [
      "#20",
      3,
      0
    ],
    "457": [
      "iconst_2",
      3,
      0
    ],
    "458": [
      "iload",
      3,
      0
    ],
    "459": [
      "#19",
      3,
      0
    ],
    "460": [
      "imul",
      3,
      0
    ],
    "461": [
      "iadd",
      3,
      0
    ],
    "462": [
      "istore",
      3,
      0
    ],
    "463": [
      "#20",
      3,
      0
    ],
    "464": [
      "goto",
      3,
      4
    ],
    "465": [
      "-183",
      3,
      4
    ],
    "467": [
      "aload",
      2,
      0
    ],
    "468": [
      "#6",
      2,
      0
    ],
    "469": [
      "astore",
      2,
      0
    ],
    "470": [
      "#20",
      2,
      0
    ],
    "471": [
      "aload",
      2,
      0
    ],
    "472": [
      "#18",
      2,
      0
    ],
    "473": [
      "astore",
      2,
      0
    ],
    "474": [
      "#6",
      2,
      0
    ],
    "475": [
      "aload",
      2,
      0
    ],
    "476": [
      "#20",
      2,
      0
    ],
    "477": [
      "astore",
      2,
      0
    ],
    "478": [
      "#18",
      2,
      0
    ],
    "479": [
      "iload",
      2,
      0
    ],
    "480": [
      "#19",
      2,
      0
    ],
    "481": [
      "iconst_1",
      2,
      0
    ],
    "482": [
      "ishl",
      2,
      0
    ],
    "483": [
      "istore",
      2,
      0
    ],
    "484": [
      "#19",
      2,
      0
    ],
    "485": [
      "goto",
      2,
      4
    ],
    "486": [
      "-213",
      2,
      4
    ],
    "488": [
      "lconst_0",
      1,
      0
    ],
    "489": [
      "lstore",
      1,
      0
    ],
    "490": [
      "#19",
      1,
      0
    ],
    "491": [
      "lconst_1",
      1,
      0
    ],
    "492": [
      "lstore",
      1,
      0
    ],
    "493": [
      "#21",
      1,
      0
    ],
    "494": [
      "aload",
      1,
      0
    ],
    "495": [
      "#6",
      1,
      0
    ],
    "496": [
      "iconst_0",
      1,
      0
    ],
    "497": [
      "aaload",
      1,
      0
    ],
    "498": [
      "astore",
      1,
      0
    ],
    "499": [
      "#15",
      1,
      0
    ],
    "500": [
      "iconst_1",
      2,
      4
    ],
    "501": [
      "istore",
      2,
      4
    ],
    "502": [
      "#23",
      2,
      4
    ],
    "503": [
      "iload",
      2,
      4
    ],
    "504": [
      "#23",
      2,
      4
    ],
    "505": [
      "iload_3",
      2,
      4
    ],
    "506": [
      "if_icmpge",
      2,
      4
    ],
    "507": [
      "63",
      2,
      4
    ],
    "509": [
      "aload",
      2,
      0
    ],
    "510": [
      "#6",
      2,
      0
    ],
    "511": [
      "iload",
      2,
      0
    ],
    "512": [
      "#23",
      2,
      0
    ],
    "513": [
      "aaload",
      2,
      0
    ],
    "514": [
      "astore",
      2,
      0
    ],
    "515": [
      "#24",
      2,
      0
    ],
    "516": [
      "aload",
      3,
      1
    ],
    "517": [
      "#24",
      3,
      1
    ],
    "518": [
      "invokevirtual",
      3,
      1
    ],
    "519": [
      "org/apache/commons/math3/util/Pair.getSecond:()Ljava/lang/Object;",
      3,
      1
    ],
    "521": [
      "checkcast",
      3,
      1
    ],
    "522": [
      "java/lang/Double",
      3,
      1
    ],
    "524": [
      "aload",
      3,
      1
    ],
    "525": [
      "#15",
      3,
      1
    ],
    "526": [
      "invokevirtual",
      3,
      1
    ],
    "527": [
      "org/apache/commons/math3/util/Pair.getSecond:()Ljava/lang/Object;",
      3,
      1
    ],
    "529": [
      "invokevirtual",
      3,
      1
    ],
    "530": [
      "java/lang/Double.equals:(Ljava/lang/Object;)Z",
      3,
      1
    ],
    "532": [
      "ifeq",
      3,
      1
    ],
    "533": [
      "12",
      3,
      1
    ],
    "535": [
      "lload",
      3,
      0
    ],
    "536": [
      "#21",
      3,
      0
    ],
    "537": [
      "lconst_1",
      3,
      0
    ],
    "538": [
      "ladd",
      3,
      0
    ],
    "539": [
      "lstore",
      3,
      0
    ],
    "540": [
      "#21",
      3,
      0
    ],
    "541": [
      "goto",
      3,
      0
    ],
    "542": [
      "18",
      3,
      0
    ],
    "544": [
      "lload",
      3,
      0
    ],
    "545": [
      "#19",
      3,
      0
    ],
    "546": [
      "lload",
      3,
      0
    ],
    "547": [
      "#21",
      3,
      0
    ],
    "548": [
      "lconst_1",
      3,
      0
    ],
    "549": [
      "lsub",
      3,
      0
    ],
    "550": [
      "invokestatic",
      3,
      0
    ],
    "551": [
      "org/apache/commons/math3/stat/correlation/KendallsCorrelation.sum:(J)J",
      3,
      0
    ],
    "553": [
      "ladd",
      3,
      0
    ],
    "554": [
      "lstore",
      3,
      0
    ],
    "555": [
      "#19",
      3,
      0
    ],
    "556": [
      "lconst_1",
      3,
      0
    ],
    "557": [
      "lstore",
      3,
      0
    ],
    "558": [
      "#21",
      3,
      0
    ],
    "559": [
      "aload",
      2,
      0
    ],
    "560": [
      "#24",
      2,
      0
    ],
    "561": [
      "astore",
      2,
      0
    ],
    "562": [
      "#15",
      2,
      0
    ],
    "563": [
      "iinc",
      2,
      0
    ],
    "564": [
      "#23",
      2,
      0
    ],
    "565": [
      "-89",
      2,
      0
    ],
    "566": [
      "goto",
      2,
      4
    ],
    "567": [
      "-63",
      2,
      4
    ],
    "569": [
      "lload",
      1,
      0
    ],
    "570": [
      "#19",
      1,
      0
    ],
    "571": [
      "lload",
      1,
      0
    ],
    "572": [
      "#21",
      1,
      0
    ],
    "573": [
      "lconst_1",
      1,
      0
    ],
    "574": [
      "lsub",
      1,
      0
    ],
    "575": [
      "invokestatic",
      1,
      0
    ],
    "576": [
      "org/apache/commons/math3/stat/correlation/KendallsCorrelation.sum:(J)J",
      1,
      0
    ],
    "578": [
      "ladd",
      1,
      0
    ],
    "579": [
      "lstore",
      1,
      0
    ],
    "580": [
      "#19",
      1,
      0
    ],
    "581": [
      "lload",
      1,
      0
    ],
    "582": [
      "#4",
      1,
      0
    ],
    "583": [
      "lload",
      1,
      0
    ],
    "584": [
      "#7",
      1,
      0
    ],
    "585": [
      "lsub",
      1,
      0
    ],
    "586": [
      "lload",
      1,
      0
    ],
    "587": [
      "#19",
      1,
      0
    ],
    "588": [
      "lsub",
      1,
      0
    ],
    "589": [
      "lload",
      1,
      0
    ],
    "590": [
      "#9",
      1,
      0
    ],
    "591": [
      "ladd",
      1,
      0
    ],
    "592": [
      "ldc2_w",
      1,
      0
    ],
    "593": [
      "2",
      1,
      0
    ],
    "595": [
      "lload",
      1,
      0
    ],
    "596": [
      "#16",
      1,
      0
    ],
    "597": [
      "lmul",
      1,
      0
    ],
    "598": [
      "lsub",
      1,
      0
    ],
    "599": [
      "lstore",
      1,
      0
    ],
    "600": [
      "#23",
      1,
      0
    ],
    "601": [
      "lload",
      1,
      0
    ],
    "602": [
      "#4",
      1,
      0
    ],
    "603": [
      "lload",
      1,
      0
    ],
    "604": [
      "#7",
      1,
      0
    ],
    "605": [
      "lsub",
      1,
      0
    ],
    "606": [
      "l2d",
      1,
      0
    ],
    "607": [
      "lload",
      1,
      0
    ],
    "608": [
      "#4",
      1,
      0
    ],
    "609": [
      "lload",
      1,
      0
    ],
    "610": [
      "#19",
      1,
      0
    ],
    "611": [
      "lsub",
      1,
      0
    ],
    "612": [
      "l2d",
      1,
      0
    ],
    "613": [
      "dmul",
      1,
      0
    ],
    "614": [
      "dstore",
      1,
      0
    ],
    "615": [
      "#25",
      1,
      0
    ],
    "616": [
      "lload",
      1,
      0
    ],
    "617": [
      "#23",
      1,
      0
    ],
    "618": [
      "l2d",
      1,
      0
    ],
    "619": [
      "dload",
      1,
      0
    ],
    "620": [
      "#25",
      1,
      0
    ],
    "621": [
      "invokestatic",
      1,
      0
    ],
    "622": [
      "org/apache/commons/math3/util/FastMath.sqrt:(D)D",
      1,
      0
    ],
    "624": [
      "ddiv",
      1,
      0
    ],
    "625": [
      "dreturn",
      1,
      0
    ]
  },
  "sum": {
    "0": [
      "lload_0",
      0,
      0
    ],
    "1": [
      "lload_0",
      0,
      0
    ],
    "2": [
      "lconst_1",
      0,
      0
    ],
    "3": [
      "ladd",
      0,
      0
    ],
    "4": [
      "lmul",
      0,
      0
    ],
    "5": [
      "ldc2_w",
      0,
      0
    ],
    "6": [
      "2",
      0,
      0
    ],
    "8": [
      "ldiv",
      0,
      0
    ],
    "9": [
      "lreturn",
      0,
      0
    ]
  }
}