{
  "emptyIterator": {
    "0": [
      "invokestatic",
      0,
      0
    ],
    "1": [
      "org/apache/commons/collections4/iterators/EmptyIterator.resettableEmptyIterator:()Lorg/apache/commons/collections4/ResettableIterator;",
      0,
      0
    ],
    "3": [
      "areturn",
      0,
      0
    ]
  },
  "emptyListIterator": {
    "0": [
      "invokestatic",
      0,
      0
    ],
    "1": [
      "org/apache/commons/collections4/iterators/EmptyListIterator.resettableEmptyListIterator:()Lorg/apache/commons/collections4/ResettableListIterator;",
      0,
      0
    ],
    "3": [
      "areturn",
      0,
      0
    ]
  },
  "emptyOrderedIterator": {
    "0": [
      "invokestatic",
      0,
      0
    ],
    "1": [
      "org/apache/commons/collections4/iterators/EmptyOrderedIterator.emptyOrderedIterator:()Lorg/apache/commons/collections4/OrderedIterator;",
      0,
      0
    ],
    "3": [
      "areturn",
      0,
      0
    ]
  },
  "emptyMapIterator": {
    "0": [
      "invokestatic",
      0,
      0
    ],
    "1": [
      "org/apache/commons/collections4/iterators/EmptyMapIterator.emptyMapIterator:()Lorg/apache/commons/collections4/MapIterator;",
      0,
      0
    ],
    "3": [
      "areturn",
      0,
      0
    ]
  },
  "emptyOrderedMapIterator": {
    "0": [
      "invokestatic",
      0,
      0
    ],
    "1": [
      "org/apache/commons/collections4/iterators/EmptyOrderedMapIterator.emptyOrderedMapIterator:()Lorg/apache/commons/collections4/OrderedMapIterator;",
      0,
      0
    ],
    "3": [
      "areturn",
      0,
      0
    ]
  },
  "singletonIterator": {
    "0": [
      "new",
      0,
      0
    ],
    "1": [
      "org/apache/commons/collections4/iterators/SingletonIterator",
      0,
      0
    ],
    "3": [
      "dup",
      0,
      0
    ],
    "4": [
      "aload_0",
      0,
      0
    ],
    "5": [
      "invokespecial",
      0,
      0
    ],
    "6": [
      "org/apache/commons/collections4/iterators/SingletonIterator.<init>:(Ljava/lang/Object;)V",
      0,
      0
    ],
    "8": [
      "areturn",
      0,
      0
    ]
  },
  "singletonListIterator": {
    "0": [
      "new",
      0,
      0
    ],
    "1": [
      "org/apache/commons/collections4/iterators/SingletonListIterator",
      0,
      0
    ],
    "3": [
      "dup",
      0,
      0
    ],
    "4": [
      "aload_0",
      0,
      0
    ],
    "5": [
      "invokespecial",
      0,
      0
    ],
    "6": [
      "org/apache/commons/collections4/iterators/SingletonListIterator.<init>:(Ljava/lang/Object;)V",
      0,
      0
    ],
    "8": [
      "areturn",
      0,
      0
    ]
  },
  "arrayIterator": {
    "0": [
      "new",
      0,
      0
    ],
    "1": [
      "org/apache/commons/collections4/iterators/ArrayIterator",
      0,
      0
    ],
    "3": [
      "dup",
      0,
      0
    ],
    "4": [
      "aload_0",
      0,
      0
    ],
    "5": [
      "iload_1",
      0,
      0
    ],
    "6": [
      "iload_2",
      0,
      0
    ],
    "7": [
      "invokespecial",
      0,
      0
    ],
    "8": [
      "org/apache/commons/collections4/iterators/ArrayIterator.<init>:(Ljava/lang/Object;II)V",
      0,
      0
    ],
    "10": [
      "areturn",
      0,
      0
    ]
  },
  "arrayListIterator": {
    "0": [
      "new",
      0,
      0
    ],
    "1": [
      "org/apache/commons/collections4/iterators/ArrayListIterator",
      0,
      0
    ],
    "3": [
      "dup",
      0,
      0
    ],
    "4": [
      "aload_0",
      0,
      0
    ],
    "5": [
      "iload_1",
      0,
      0
    ],
    "6": [
      "iload_2",
      0,
      0
    ],
    "7": [
      "invokespecial",
      0,
      0
    ],
    "8": [
      "org/apache/commons/collections4/iterators/ArrayListIterator.<init>:(Ljava/lang/Object;II)V",
      0,
      0
    ],
    "10": [
      "areturn",
      0,
      0
    ]
  },
  "boundedIterator": {
    "0": [
      "new",
      0,
      0
    ],
    "1": [
      "org/apache/commons/collections4/iterators/BoundedIterator",
      0,
      0
    ],
    "3": [
      "dup",
      0,
      0
    ],
    "4": [
      "aload_0",
      0,
      0
    ],
    "5": [
      "lload_1",
      0,
      0
    ],
    "6": [
      "lload_3",
      0,
      0
    ],
    "7": [
      "invokespecial",
      0,
      0
    ],
    "8": [
      "org/apache/commons/collections4/iterators/BoundedIterator.<init>:(Ljava/util/Iterator;JJ)V",
      0,
      0
    ],
    "10": [
      "areturn",
      0,
      0
    ]
  },
  "unmodifiableIterator": {
    "0": [
      "aload_0",
      0,
      0
    ],
    "1": [
      "invokestatic",
      0,
      0
    ],
    "2": [
      "org/apache/commons/collections4/iterators/UnmodifiableIterator.unmodifiableIterator:(Ljava/util/Iterator;)Ljava/util/Iterator;",
      0,
      0
    ],
    "4": [
      "areturn",
      0,
      0
    ]
  },
  "unmodifiableListIterator": {
    "0": [
      "aload_0",
      0,
      0
    ],
    "1": [
      "invokestatic",
      0,
      0
    ],
    "2": [
      "org/apache/commons/collections4/iterators/UnmodifiableListIterator.umodifiableListIterator:(Ljava/util/ListIterator;)Ljava/util/ListIterator;",
      0,
      0
    ],
    "4": [
      "areturn",
      0,
      0
    ]
  },
  "unmodifiableMapIterator": {
    "0": [
      "aload_0",
      0,
      0
    ],
    "1": [
      "invokestatic",
      0,
      0
    ],
    "2": [
      "org/apache/commons/collections4/iterators/UnmodifiableMapIterator.unmodifiableMapIterator:(Lorg/apache/commons/collections4/MapIterator;)Lorg/apache/commons/collections4/MapIterator;",
      0,
      0
    ],
    "4": [
      "areturn",
      0,
      0
    ]
  },
  "chainedIterator": {
    "0": [
      "new",
      0,
      0
    ],
    "1": [
      "org/apache/commons/collections4/iterators/IteratorChain",
      0,
      0
    ],
    "3": [
      "dup",
      0,
      0
    ],
    "4": [
      "aload_0",
      0,
      0
    ],
    "5": [
      "invokespecial",
      0,
      0
    ],
    "6": [
      "org/apache/commons/collections4/iterators/IteratorChain.<init>:(Ljava/util/Collection;)V",
      0,
      0
    ],
    "8": [
      "areturn",
      0,
      0
    ]
  },
  "collatedIterator": {
    "0": [
      "aload_0",
      0,
      0
    ],
    "1": [
      "ifnonnull",
      0,
      0
    ],
    "2": [
      "9",
      0,
      0
    ],
    "4": [
      "getstatic",
      0,
      0
    ],
    "5": [
      "org/apache/commons/collections4/ComparatorUtils.NATURAL_COMPARATOR:Ljava/util/Comparator;",
      0,
      0
    ],
    "7": [
      "goto",
      0,
      0
    ],
    "8": [
      "4",
      0,
      0
    ],
    "10": [
      "aload_0",
      0,
      0
    ],
    "11": [
      "astore_2",
      0,
      0
    ],
    "12": [
      "new",
      0,
      0
    ],
    "13": [
      "org/apache/commons/collections4/iterators/CollatingIterator",
      0,
      0
    ],
    "15": [
      "dup",
      0,
      0
    ],
    "16": [
      "aload_2",
      0,
      0
    ],
    "17": [
      "aload_1",
      0,
      0
    ],
    "18": [
      "invokespecial",
      0,
      0
    ],
    "19": [
      "org/apache/commons/collections4/iterators/CollatingIterator.<init>:(Ljava/util/Comparator;Ljava/util/Collection;)V",
      0,
      0
    ],
    "21": [
      "areturn",
      0,
      0
    ]
  },
  "objectGraphIterator": {
    "0": [
      "new",
      0,
      0
    ],
    "1": [
      "org/apache/commons/collections4/iterators/ObjectGraphIterator",
      0,
      0
    ],
    "3": [
      "dup",
      0,
      0
    ],
    "4": [
      "aload_0",
      0,
      0
    ],
    "5": [
      "aload_1",
      0,
      0
    ],
    "6": [
      "invokespecial",
      0,
      0
    ],
    "7": [
      "org/apache/commons/collections4/iterators/ObjectGraphIterator.<init>:(Ljava/lang/Object;Lorg/apache/commons/collections4/Transformer;)V",
      0,
      0
    ],
    "9": [
      "areturn",
      0,
      0
    ]
  },
  "transformedIterator": {
    "0": [
      "aload_0",
      1,
      1
    ],
    "1": [
      "ifnonnull",
      1,
      1
    ],
    "2": [
      "13",
      1,
      1
    ],
    "4": [
      "new",
      1,
      0
    ],
    "5": [
      "java/lang/NullPointerException",
      1,
      0
    ],
    "7": [
      "dup",
      1,
      0
    ],
    "8": [
      "ldc",
      1,
      0
    ],
    "9": [
      "Iterator must not be null",
      1,
      0
    ],
    "10": [
      "invokespecial",
      1,
      0
    ],
    "11": [
      "java/lang/NullPointerException.<init>:(Ljava/lang/String;)V",
      1,
      0
    ],
    "13": [
      "athrow",
      1,
      0
    ],
    "14": [
      "aload_1",
      1,
      1
    ],
    "15": [
      "ifnonnull",
      1,
      1
    ],
    "16": [
      "13",
      1,
      1
    ],
    "18": [
      "new",
      1,
      0
    ],
    "19": [
      "java/lang/NullPointerException",
      1,
      0
    ],
    "21": [
      "dup",
      1,
      0
    ],
    "22": [
      "ldc",
      1,
      0
    ],
    "23": [
      "Transformer must not be null",
      1,
      0
    ],
    "24": [
      "invokespecial",
      1,
      0
    ],
    "25": [
      "java/lang/NullPointerException.<init>:(Ljava/lang/String;)V",
      1,
      0
    ],
    "27": [
      "athrow",
      1,
      0
    ],
    "28": [
      "new",
      0,
      0
    ],
    "29": [
      "org/apache/commons/collections4/iterators/TransformIterator",
      0,
      0
    ],
    "31": [
      "dup",
      0,
      0
    ],
    "32": [
      "aload_0",
      0,
      0
    ],
    "33": [
      "aload_1",
      0,
      0
    ],
    "34": [
      "invokespecial",
      0,
      0
    ],
    "35": [
      "org/apache/commons/collections4/iterators/TransformIterator.<init>:(Ljava/util/Iterator;Lorg/apache/commons/collections4/Transformer;)V",
      0,
      0
    ],
    "37": [
      "areturn",
      0,
      0
    ]
  },
  "filteredIterator": {
    "0": [
      "aload_0",
      1,
      1
    ],
    "1": [
      "ifnonnull",
      1,
      1
    ],
    "2": [
      "13",
      1,
      1
    ],
    "4": [
      "new",
      1,
      0
    ],
    "5": [
      "java/lang/NullPointerException",
      1,
      0
    ],
    "7": [
      "dup",
      1,
      0
    ],
    "8": [
      "ldc",
      1,
      0
    ],
    "9": [
      "Iterator must not be null",
      1,
      0
    ],
    "10": [
      "invokespecial",
      1,
      0
    ],
    "11": [
      "java/lang/NullPointerException.<init>:(Ljava/lang/String;)V",
      1,
      0
    ],
    "13": [
      "athrow",
      1,
      0
    ],
    "14": [
      "aload_1",
      1,
      1
    ],
    "15": [
      "ifnonnull",
      1,
      1
    ],
    "16": [
      "13",
      1,
      1
    ],
    "18": [
      "new",
      1,
      0
    ],
    "19": [
      "java/lang/NullPointerException",
      1,
      0
    ],
    "21": [
      "dup",
      1,
      0
    ],
    "22": [
      "ldc",
      1,
      0
    ],
    "23": [
      "Predicate must not be null",
      1,
      0
    ],
    "24": [
      "invokespecial",
      1,
      0
    ],
    "25": [
      "java/lang/NullPointerException.<init>:(Ljava/lang/String;)V",
      1,
      0
    ],
    "27": [
      "athrow",
      1,
      0
    ],
    "28": [
      "new",
      0,
      0
    ],
    "29": [
      "org/apache/commons/collections4/iterators/FilterIterator",
      0,
      0
    ],
    "31": [
      "dup",
      0,
      0
    ],
    "32": [
      "aload_0",
      0,
      0
    ],
    "33": [
      "aload_1",
      0,
      0
    ],
    "34": [
      "invokespecial",
      0,
      0
    ],
    "35": [
      "org/apache/commons/collections4/iterators/FilterIterator.<init>:(Ljava/util/Iterator;Lorg/apache/commons/collections4/Predicate;)V",
      0,
      0
    ],
    "37": [
      "areturn",
      0,
      0
    ]
  },
  "filteredListIterator": {
    "0": [
      "aload_0",
      1,
      1
    ],
    "1": [
      "ifnonnull",
      1,
      1
    ],
    "2": [
      "13",
      1,
      1
    ],
    "4": [
      "new",
      1,
      0
    ],
    "5": [
      "java/lang/NullPointerException",
      1,
      0
    ],
    "7": [
      "dup",
      1,
      0
    ],
    "8": [
      "ldc",
      1,
      0
    ],
    "9": [
      "ListIterator must not be null",
      1,
      0
    ],
    "10": [
      "invokespecial",
      1,
      0
    ],
    "11": [
      "java/lang/NullPointerException.<init>:(Ljava/lang/String;)V",
      1,
      0
    ],
    "13": [
      "athrow",
      1,
      0
    ],
    "14": [
      "aload_1",
      1,
      1
    ],
    "15": [
      "ifnonnull",
      1,
      1
    ],
    "16": [
      "13",
      1,
      1
    ],
    "18": [
      "new",
      1,
      0
    ],
    "19": [
      "java/lang/NullPointerException",
      1,
      0
    ],
    "21": [
      "dup",
      1,
      0
    ],
    "22": [
      "ldc",
      1,
      0
    ],
    "23": [
      "Predicate must not be null",
      1,
      0
    ],
    "24": [
      "invokespecial",
      1,
      0
    ],
    "25": [
      "java/lang/NullPointerException.<init>:(Ljava/lang/String;)V",
      1,
      0
    ],
    "27": [
      "athrow",
      1,
      0
    ],
    "28": [
      "new",
      0,
      0
    ],
    "29": [
      "org/apache/commons/collections4/iterators/FilterListIterator",
      0,
      0
    ],
    "31": [
      "dup",
      0,
      0
    ],
    "32": [
      "aload_0",
      0,
      0
    ],
    "33": [
      "aload_1",
      0,
      0
    ],
    "34": [
      "invokespecial",
      0,
      0
    ],
    "35": [
      "org/apache/commons/collections4/iterators/FilterListIterator.<init>:(Ljava/util/ListIterator;Lorg/apache/commons/collections4/Predicate;)V",
      0,
      0
    ],
    "37": [
      "areturn",
      0,
      0
    ]
  },
  "loopingIterator": {
    "0": [
      "aload_0",
      1,
      1
    ],
    "1": [
      "ifnonnull",
      1,
      1
    ],
    "2": [
      "13",
      1,
      1
    ],
    "4": [
      "new",
      1,
      0
    ],
    "5": [
      "java/lang/NullPointerException",
      1,
      0
    ],
    "7": [
      "dup",
      1,
      0
    ],
    "8": [
      "ldc",
      1,
      0
    ],
    "9": [
      "Collection must not be null",
      1,
      0
    ],
    "10": [
      "invokespecial",
      1,
      0
    ],
    "11": [
      "java/lang/NullPointerException.<init>:(Ljava/lang/String;)V",
      1,
      0
    ],
    "13": [
      "athrow",
      1,
      0
    ],
    "14": [
      "new",
      0,
      0
    ],
    "15": [
      "org/apache/commons/collections4/iterators/LoopingIterator",
      0,
      0
    ],
    "17": [
      "dup",
      0,
      0
    ],
    "18": [
      "aload_0",
      0,
      0
    ],
    "19": [
      "invokespecial",
      0,
      0
    ],
    "20": [
      "org/apache/commons/collections4/iterators/LoopingIterator.<init>:(Ljava/util/Collection;)V",
      0,
      0
    ],
    "22": [
      "areturn",
      0,
      0
    ]
  },
  "loopingListIterator": {
    "0": [
      "aload_0",
      1,
      1
    ],
    "1": [
      "ifnonnull",
      1,
      1
    ],
    "2": [
      "13",
      1,
      1
    ],
    "4": [
      "new",
      1,
      0
    ],
    "5": [
      "java/lang/NullPointerException",
      1,
      0
    ],
    "7": [
      "dup",
      1,
      0
    ],
    "8": [
      "ldc",
      1,
      0
    ],
    "9": [
      "List must not be null",
      1,
      0
    ],
    "10": [
      "invokespecial",
      1,
      0
    ],
    "11": [
      "java/lang/NullPointerException.<init>:(Ljava/lang/String;)V",
      1,
      0
    ],
    "13": [
      "athrow",
      1,
      0
    ],
    "14": [
      "new",
      0,
      0
    ],
    "15": [
      "org/apache/commons/collections4/iterators/LoopingListIterator",
      0,
      0
    ],
    "17": [
      "dup",
      0,
      0
    ],
    "18": [
      "aload_0",
      0,
      0
    ],
    "19": [
      "invokespecial",
      0,
      0
    ],
    "20": [
      "org/apache/commons/collections4/iterators/LoopingListIterator.<init>:(Ljava/util/List;)V",
      0,
      0
    ],
    "22": [
      "areturn",
      0,
      0
    ]
  },
  "nodeListIterator": {
    "0": [
      "aload_0",
      1,
      1
    ],
    "1": [
      "ifnonnull",
      1,
      1
    ],
    "2": [
      "13",
      1,
      1
    ],
    "4": [
      "new",
      1,
      0
    ],
    "5": [
      "java/lang/NullPointerException",
      1,
      0
    ],
    "7": [
      "dup",
      1,
      0
    ],
    "8": [
      "ldc",
      1,
      0
    ],
    "9": [
      "Node must not be null",
      1,
      0
    ],
    "10": [
      "invokespecial",
      1,
      0
    ],
    "11": [
      "java/lang/NullPointerException.<init>:(Ljava/lang/String;)V",
      1,
      0
    ],
    "13": [
      "athrow",
      1,
      0
    ],
    "14": [
      "new",
      0,
      0
    ],
    "15": [
      "org/apache/commons/collections4/iterators/NodeListIterator",
      0,
      0
    ],
    "17": [
      "dup",
      0,
      0
    ],
    "18": [
      "aload_0",
      0,
      0
    ],
    "19": [
      "invokespecial",
      0,
      0
    ],
    "20": [
      "org/apache/commons/collections4/iterators/NodeListIterator.<init>:(Lorg/w3c/dom/Node;)V",
      0,
      0
    ],
    "22": [
      "areturn",
      0,
      0
    ]
  },
  "peekingIterator": {
    "0": [
      "aload_0",
      0,
      0
    ],
    "1": [
      "invokestatic",
      0,
      0
    ],
    "2": [
      "org/apache/commons/collections4/iterators/PeekingIterator.peekingIterator:(Ljava/util/Iterator;)Lorg/apache/commons/collections4/iterators/PeekingIterator;",
      0,
      0
    ],
    "4": [
      "areturn",
      0,
      0
    ]
  },
  "pushbackIterator": {
    "0": [
      "aload_0",
      0,
      0
    ],
    "1": [
      "invokestatic",
      0,
      0
    ],
    "2": [
      "org/apache/commons/collections4/iterators/PushbackIterator.pushbackIterator:(Ljava/util/Iterator;)Lorg/apache/commons/collections4/iterators/PushbackIterator;",
      0,
      0
    ],
    "4": [
      "areturn",
      0,
      0
    ]
  },
  "skippingIterator": {
    "0": [
      "new",
      0,
      0
    ],
    "1": [
      "org/apache/commons/collections4/iterators/SkippingIterator",
      0,
      0
    ],
    "3": [
      "dup",
      0,
      0
    ],
    "4": [
      "aload_0",
      0,
      0
    ],
    "5": [
      "lload_1",
      0,
      0
    ],
    "6": [
      "invokespecial",
      0,
      0
    ],
    "7": [
      "org/apache/commons/collections4/iterators/SkippingIterator.<init>:(Ljava/util/Iterator;J)V",
      0,
      0
    ],
    "9": [
      "areturn",
      0,
      0
    ]
  },
  "zippingIterator": {
    "0": [
      "new",
      0,
      0
    ],
    "1": [
      "org/apache/commons/collections4/iterators/ZippingIterator",
      0,
      0
    ],
    "3": [
      "dup",
      0,
      0
    ],
    "4": [
      "aload_0",
      0,
      0
    ],
    "5": [
      "invokespecial",
      0,
      0
    ],
    "6": [
      "org/apache/commons/collections4/iterators/ZippingIterator.<init>:([Ljava/util/Iterator;)V",
      0,
      0
    ],
    "8": [
      "areturn",
      0,
      0
    ]
  },
  "asIterator": {
    "0": [
      "aload_0",
      1,
      1
    ],
    "1": [
      "ifnonnull",
      1,
      1
    ],
    "2": [
      "13",
      1,
      1
    ],
    "4": [
      "new",
      1,
      0
    ],
    "5": [
      "java/lang/NullPointerException",
      1,
      0
    ],
    "7": [
      "dup",
      1,
      0
    ],
    "8": [
      "ldc",
      1,
      0
    ],
    "9": [
      "Enumeration must not be null",
      1,
      0
    ],
    "10": [
      "invokespecial",
      1,
      0
    ],
    "11": [
      "java/lang/NullPointerException.<init>:(Ljava/lang/String;)V",
      1,
      0
    ],
    "13": [
      "athrow",
      1,
      0
    ],
    "14": [
      "aload_1",
      1,
      1
    ],
    "15": [
      "ifnonnull",
      1,
      1
    ],
    "16": [
      "13",
      1,
      1
    ],
    "18": [
      "new",
      1,
      0
    ],
    "19": [
      "java/lang/NullPointerException",
      1,
      0
    ],
    "21": [
      "dup",
      1,
      0
    ],
    "22": [
      "ldc",
      1,
      0
    ],
    "23": [
      "Collection must not be null",
      1,
      0
    ],
    "24": [
      "invokespecial",
      1,
      0
    ],
    "25": [
      "java/lang/NullPointerException.<init>:(Ljava/lang/String;)V",
      1,
      0
    ],
    "27": [
      "athrow",
      1,
      0
    ],
    "28": [
      "new",
      0,
      0
    ],
    "29": [
      "org/apache/commons/collections4/iterators/EnumerationIterator",
      0,
      0
    ],
    "31": [
      "dup",
      0,
      0
    ],
    "32": [
      "aload_0",
      0,
      0
    ],
    "33": [
      "aload_1",
      0,
      0
    ],
    "34": [
      "invokespecial",
      0,
      0
    ],
    "35": [
      "org/apache/commons/collections4/iterators/EnumerationIterator.<init>:(Ljava/util/Enumeration;Ljava/util/Collection;)V",
      0,
      0
    ],
    "37": [
      "areturn",
      0,
      0
    ]
  },
  "asEnumeration": {
    "0": [
      "aload_0",
      1,
      1
    ],
    "1": [
      "ifnonnull",
      1,
      1
    ],
    "2": [
      "13",
      1,
      1
    ],
    "4": [
      "new",
      1,
      0
    ],
    "5": [
      "java/lang/NullPointerException",
      1,
      0
    ],
    "7": [
      "dup",
      1,
      0
    ],
    "8": [
      "ldc",
      1,
      0
    ],
    "9": [
      "Iterator must not be null",
      1,
      0
    ],
    "10": [
      "invokespecial",
      1,
      0
    ],
    "11": [
      "java/lang/NullPointerException.<init>:(Ljava/lang/String;)V",
      1,
      0
    ],
    "13": [
      "athrow",
      1,
      0
    ],
    "14": [
      "new",
      0,
      0
    ],
    "15": [
      "org/apache/commons/collections4/iterators/IteratorEnumeration",
      0,
      0
    ],
    "17": [
      "dup",
      0,
      0
    ],
    "18": [
      "aload_0",
      0,
      0
    ],
    "19": [
      "invokespecial",
      0,
      0
    ],
    "20": [
      "org/apache/commons/collections4/iterators/IteratorEnumeration.<init>:(Ljava/util/Iterator;)V",
      0,
      0
    ],
    "22": [
      "areturn",
      0,
      0
    ]
  },
  "asIterable": {
    "0": [
      "aload_0",
      1,
      1
    ],
    "1": [
      "ifnonnull",
      1,
      1
    ],
    "2": [
      "13",
      1,
      1
    ],
    "4": [
      "new",
      1,
      0
    ],
    "5": [
      "java/lang/NullPointerException",
      1,
      0
    ],
    "7": [
      "dup",
      1,
      0
    ],
    "8": [
      "ldc",
      1,
      0
    ],
    "9": [
      "Iterator must not be null",
      1,
      0
    ],
    "10": [
      "invokespecial",
      1,
      0
    ],
    "11": [
      "java/lang/NullPointerException.<init>:(Ljava/lang/String;)V",
      1,
      0
    ],
    "13": [
      "athrow",
      1,
      0
    ],
    "14": [
      "new",
      0,
      0
    ],
    "15": [
      "org/apache/commons/collections4/iterators/IteratorIterable",
      0,
      0
    ],
    "17": [
      "dup",
      0,
      0
    ],
    "18": [
      "aload_0",
      0,
      0
    ],
    "19": [
      "iconst_0",
      0,
      0
    ],
    "20": [
      "invokespecial",
      0,
      0
    ],
    "21": [
      "org/apache/commons/collections4/iterators/IteratorIterable.<init>:(Ljava/util/Iterator;Z)V",
      0,
      0
    ],
    "23": [
      "areturn",
      0,
      0
    ]
  },
  "asMultipleUseIterable": {
    "0": [
      "aload_0",
      1,
      1
    ],
    "1": [
      "ifnonnull",
      1,
      1
    ],
    "2": [
      "13",
      1,
      1
    ],
    "4": [
      "new",
      1,
      0
    ],
    "5": [
      "java/lang/NullPointerException",
      1,
      0
    ],
    "7": [
      "dup",
      1,
      0
    ],
    "8": [
      "ldc",
      1,
      0
    ],
    "9": [
      "Iterator must not be null",
      1,
      0
    ],
    "10": [
      "invokespecial",
      1,
      0
    ],
    "11": [
      "java/lang/NullPointerException.<init>:(Ljava/lang/String;)V",
      1,
      0
    ],
    "13": [
      "athrow",
      1,
      0
    ],
    "14": [
      "new",
      0,
      0
    ],
    "15": [
      "org/apache/commons/collections4/iterators/IteratorIterable",
      0,
      0
    ],
    "17": [
      "dup",
      0,
      0
    ],
    "18": [
      "aload_0",
      0,
      0
    ],
    "19": [
      "iconst_1",
      0,
      0
    ],
    "20": [
      "invokespecial",
      0,
      0
    ],
    "21": [
      "org/apache/commons/collections4/iterators/IteratorIterable.<init>:(Ljava/util/Iterator;Z)V",
      0,
      0
    ],
    "23": [
      "areturn",
      0,
      0
    ]
  },
  "toListIterator": {
    "0": [
      "aload_0",
      1,
      1
    ],
    "1": [
      "ifnonnull",
      1,
      1
    ],
    "2": [
      "13",
      1,
      1
    ],
    "4": [
      "new",
      1,
      0
    ],
    "5": [
      "java/lang/NullPointerException",
      1,
      0
    ],
    "7": [
      "dup",
      1,
      0
    ],
    "8": [
      "ldc",
      1,
      0
    ],
    "9": [
      "Iterator must not be null",
      1,
      0
    ],
    "10": [
      "invokespecial",
      1,
      0
    ],
    "11": [
      "java/lang/NullPointerException.<init>:(Ljava/lang/String;)V",
      1,
      0
    ],
    "13": [
      "athrow",
      1,
      0
    ],
    "14": [
      "new",
      0,
      0
    ],
    "15": [
      "org/apache/commons/collections4/iterators/ListIteratorWrapper",
      0,
      0
    ],
    "17": [
      "dup",
      0,
      0
    ],
    "18": [
      "aload_0",
      0,
      0
    ],
    "19": [
      "invokespecial",
      0,
      0
    ],
    "20": [
      "org/apache/commons/collections4/iterators/ListIteratorWrapper.<init>:(Ljava/util/Iterator;)V",
      0,
      0
    ],
    "22": [
      "areturn",
      0,
      0
    ]
  },
  "toArray": {
    "0": [
      "aload_0",
      1,
      1
    ],
    "1": [
      "ifnonnull",
      1,
      1
    ],
    "2": [
      "13",
      1,
      1
    ],
    "4": [
      "new",
      1,
      0
    ],
    "5": [
      "java/lang/NullPointerException",
      1,
      0
    ],
    "7": [
      "dup",
      1,
      0
    ],
    "8": [
      "ldc",
      1,
      0
    ],
    "9": [
      "Iterator must not be null",
      1,
      0
    ],
    "10": [
      "invokespecial",
      1,
      0
    ],
    "11": [
      "java/lang/NullPointerException.<init>:(Ljava/lang/String;)V",
      1,
      0
    ],
    "13": [
      "athrow",
      1,
      0
    ],
    "14": [
      "aload_1",
      1,
      1
    ],
    "15": [
      "ifnonnull",
      1,
      1
    ],
    "16": [
      "13",
      1,
      1
    ],
    "18": [
      "new",
      1,
      0
    ],
    "19": [
      "java/lang/NullPointerException",
      1,
      0
    ],
    "21": [
      "dup",
      1,
      0
    ],
    "22": [
      "ldc",
      1,
      0
    ],
    "23": [
      "Array class must not be null",
      1,
      0
    ],
    "24": [
      "invokespecial",
      1,
      0
    ],
    "25": [
      "java/lang/NullPointerException.<init>:(Ljava/lang/String;)V",
      1,
      0
    ],
    "27": [
      "athrow",
      1,
      0
    ],
    "28": [
      "aload_0",
      0,
      0
    ],
    "29": [
      "bipush",
      0,
      0
    ],
    "30": [
      "100",
      0,
      0
    ],
    "31": [
      "invokestatic",
      0,
      0
    ],
    "32": [
      "org/apache/commons/collections4/IteratorUtils.toList:(Ljava/util/Iterator;I)Ljava/util/List;",
      0,
      0
    ],
    "34": [
      "astore_2",
      0,
      0
    ],
    "35": [
      "aload_1",
      0,
      0
    ],
    "36": [
      "aload_2",
      0,
      0
    ],
    "37": [
      "invokeinterface",
      0,
      0
    ],
    "38": [
      "java/util/List.java/lang/reflect/Array",
      0,
      0
    ],
    "40": [
      "0",
      0,
      0
    ],
    "42": [
      "invokestatic",
      0,
      0
    ],
    "43": [
      "java/lang/reflect/Array.newInstance:(Ljava/lang/Class;I)Ljava/lang/Object;",
      0,
      0
    ],
    "45": [
      "checkcast",
      0,
      0
    ],
    "46": [
      "[Ljava/lang/Object;",
      0,
      0
    ],
    "48": [
      "checkcast",
      0,
      0
    ],
    "49": [
      "[Ljava/lang/Object;",
      0,
      0
    ],
    "51": [
      "astore_3",
      0,
      0
    ],
    "52": [
      "aload_2",
      0,
      0
    ],
    "53": [
      "aload_3",
      0,
      0
    ],
    "54": [
      "invokeinterface",
      0,
      0
    ],
    "55": [
      "java/util/List.java/lang/IllegalArgumentException",
      0,
      0
    ],
    "57": [
      "0",
      0,
      0
    ],
    "59": [
      "areturn",
      0,
      0
    ]
  },
  "toList": {
    "0": [
      "aload_0",
      1,
      1
    ],
    "1": [
      "ifnonnull",
      1,
      1
    ],
    "2": [
      "13",
      1,
      1
    ],
    "4": [
      "new",
      1,
      0
    ],
    "5": [
      "java/lang/NullPointerException",
      1,
      0
    ],
    "7": [
      "dup",
      1,
      0
    ],
    "8": [
      "ldc",
      1,
      0
    ],
    "9": [
      "Iterator must not be null",
      1,
      0
    ],
    "10": [
      "invokespecial",
      1,
      0
    ],
    "11": [
      "java/lang/NullPointerException.<init>:(Ljava/lang/String;)V",
      1,
      0
    ],
    "13": [
      "athrow",
      1,
      0
    ],
    "14": [
      "iload_1",
      1,
      1
    ],
    "15": [
      "iconst_1",
      1,
      1
    ],
    "16": [
      "if_icmpge",
      1,
      1
    ],
    "17": [
      "13",
      1,
      1
    ],
    "19": [
      "new",
      1,
      0
    ],
    "20": [
      "java/lang/IllegalArgumentException",
      1,
      0
    ],
    "22": [
      "dup",
      1,
      0
    ],
    "23": [
      "ldc",
      1,
      0
    ],
    "24": [
      "Estimated size must be greater than 0",
      1,
      0
    ],
    "25": [
      "invokespecial",
      1,
      0
    ],
    "26": [
      "java/lang/IllegalArgumentException.<init>:(Ljava/lang/String;)V",
      1,
      0
    ],
    "28": [
      "athrow",
      1,
      0
    ],
    "29": [
      "new",
      0,
      0
    ],
    "30": [
      "java/util/ArrayList",
      0,
      0
    ],
    "32": [
      "dup",
      0,
      0
    ],
    "33": [
      "iload_1",
      0,
      0
    ],
    "34": [
      "invokespecial",
      0,
      0
    ],
    "35": [
      "java/util/ArrayList.<init>:(I)V",
      0,
      0
    ],
    "37": [
      "astore_2",
      0,
      0
    ],
    "38": [
      "aload_0",
      1,
      3
    ],
    "39": [
      "invokeinterface",
      1,
      3
    ],
    "40": [
      "java/util/Iterator.next:()Ljava/lang/Object;",
      1,
      3
    ],
    "42": [
      "0",
      1,
      3
    ],
    "44": [
      "ifeq",
      1,
      3
    ],
    "45": [
      "19",
      1,
      3
    ],
    "47": [
      "aload_2",
      1,
      0
    ],
    "48": [
      "aload_0",
      1,
      0
    ],
    "49": [
      "invokeinterface",
      1,
      0
    ],
    "50": [
      "java/util/Iterator.add:(Ljava/lang/Object;)Z",
      1,
      0
    ],
    "52": [
      "0",
      1,
      0
    ],
    "54": [
      "invokeinterface",
      1,
      0
    ],
    "55": [
      "java/util/List.emptyIterator:()Lorg/apache/commons/collections4/ResettableIterator;",
      1,
      0
    ],
    "57": [
      "0",
      1,
      0
    ],
    "59": [
      "pop",
      1,
      0
    ],
    "60": [
      "goto",
      1,
      3
    ],
    "61": [
      "-22",
      1,
      3
    ],
    "63": [
      "aload_2",
      0,
      0
    ],
    "64": [
      "areturn",
      0,
      0
    ]
  },
  "getIterator": {
    "0": [
      "aload_0",
      1,
      1
    ],
    "1": [
      "ifnonnull",
      1,
      1
    ],
    "2": [
      "7",
      1,
      1
    ],
    "4": [
      "invokestatic",
      1,
      0
    ],
    "5": [
      "org/apache/commons/collections4/IteratorUtils.emptyIterator:()Lorg/apache/commons/collections4/ResettableIterator;",
      1,
      0
    ],
    "7": [
      "areturn",
      1,
      0
    ],
    "8": [
      "aload_0",
      1,
      1
    ],
    "9": [
      "instanceof",
      1,
      1
    ],
    "10": [
      "java/util/Iterator",
      1,
      1
    ],
    "12": [
      "ifeq",
      1,
      1
    ],
    "13": [
      "8",
      1,
      1
    ],
    "15": [
      "aload_0",
      1,
      0
    ],
    "16": [
      "checkcast",
      1,
      0
    ],
    "17": [
      "java/util/Iterator",
      1,
      0
    ],
    "19": [
      "areturn",
      1,
      0
    ],
    "20": [
      "aload_0",
      1,
      1
    ],
    "21": [
      "instanceof",
      1,
      1
    ],
    "22": [
      "java/lang/Iterable",
      1,
      1
    ],
    "24": [
      "ifeq",
      1,
      1
    ],
    "25": [
      "13",
      1,
      1
    ],
    "27": [
      "aload_0",
      1,
      0
    ],
    "28": [
      "checkcast",
      1,
      0
    ],
    "29": [
      "java/lang/Iterable",
      1,
      0
    ],
    "31": [
      "invokeinterface",
      1,
      0
    ],
    "32": [
      "java/lang/Iterable.java/util/Enumeration",
      1,
      0
    ],
    "34": [
      "0",
      1,
      0
    ],
    "36": [
      "areturn",
      1,
      0
    ],
    "37": [
      "aload_0",
      1,
      1
    ],
    "38": [
      "instanceof",
      1,
      1
    ],
    "39": [
      "[Ljava/lang/Object;",
      1,
      1
    ],
    "41": [
      "ifeq",
      1,
      1
    ],
    "42": [
      "18",
      1,
      1
    ],
    "44": [
      "new",
      1,
      0
    ],
    "45": [
      "org/apache/commons/collections4/iterators/ObjectArrayIterator",
      1,
      0
    ],
    "47": [
      "dup",
      1,
      0
    ],
    "48": [
      "aload_0",
      1,
      0
    ],
    "49": [
      "checkcast",
      1,
      0
    ],
    "50": [
      "[Ljava/lang/Object;",
      1,
      0
    ],
    "52": [
      "checkcast",
      1,
      0
    ],
    "53": [
      "[Ljava/lang/Object;",
      1,
      0
    ],
    "55": [
      "invokespecial",
      1,
      0
    ],
    "56": [
      "org/apache/commons/collections4/iterators/ObjectArrayIterator.<init>:([Ljava/lang/Object;)V",
      1,
      0
    ],
    "58": [
      "areturn",
      1,
      0
    ],
    "59": [
      "aload_0",
      1,
      1
    ],
    "60": [
      "instanceof",
      1,
      1
    ],
    "61": [
      "java/util/Enumeration",
      1,
      1
    ],
    "63": [
      "ifeq",
      1,
      1
    ],
    "64": [
      "15",
      1,
      1
    ],
    "66": [
      "new",
      1,
      0
    ],
    "67": [
      "org/apache/commons/collections4/iterators/EnumerationIterator",
      1,
      0
    ],
    "69": [
      "dup",
      1,
      0
    ],
    "70": [
      "aload_0",
      1,
      0
    ],
    "71": [
      "checkcast",
      1,
      0
    ],
    "72": [
      "java/util/Enumeration",
      1,
      0
    ],
    "74": [
      "invokespecial",
      1,
      0
    ],
    "75": [
      "org/apache/commons/collections4/iterators/EnumerationIterator.<init>:(Ljava/util/Enumeration;)V",
      1,
      0
    ],
    "77": [
      "areturn",
      1,
      0
    ],
    "78": [
      "aload_0",
      1,
      1
    ],
    "79": [
      "instanceof",
      1,
      1
    ],
    "80": [
      "java/util/Map",
      1,
      1
    ],
    "82": [
      "ifeq",
      1,
      1
    ],
    "83": [
      "18",
      1,
      1
    ],
    "85": [
      "aload_0",
      1,
      0
    ],
    "86": [
      "checkcast",
      1,
      0
    ],
    "87": [
      "java/util/Map",
      1,
      0
    ],
    "89": [
      "invokeinterface",
      1,
      0
    ],
    "90": [
      "java/util/Map.java/util/Collection",
      1,
      0
    ],
    "92": [
      "0",
      1,
      0
    ],
    "94": [
      "invokeinterface",
      1,
      0
    ],
    "95": [
      "java/util/Collection.java/util/Enumeration",
      1,
      0
    ],
    "97": [
      "0",
      1,
      0
    ],
    "99": [
      "areturn",
      1,
      0
    ],
    "100": [
      "aload_0",
      1,
      1
    ],
    "101": [
      "instanceof",
      1,
      1
    ],
    "102": [
      "org/w3c/dom/NodeList",
      1,
      1
    ],
    "104": [
      "ifeq",
      1,
      1
    ],
    "105": [
      "15",
      1,
      1
    ],
    "107": [
      "new",
      1,
      0
    ],
    "108": [
      "org/apache/commons/collections4/iterators/NodeListIterator",
      1,
      0
    ],
    "110": [
      "dup",
      1,
      0
    ],
    "111": [
      "aload_0",
      1,
      0
    ],
    "112": [
      "checkcast",
      1,
      0
    ],
    "113": [
      "org/w3c/dom/NodeList",
      1,
      0
    ],
    "115": [
      "invokespecial",
      1,
      0
    ],
    "116": [
      "org/apache/commons/collections4/iterators/NodeListIterator.<init>:(Lorg/w3c/dom/NodeList;)V",
      1,
      0
    ],
    "118": [
      "areturn",
      1,
      0
    ],
    "119": [
      "aload_0",
      1,
      1
    ],
    "120": [
      "instanceof",
      1,
      1
    ],
    "121": [
      "org/w3c/dom/Node",
      1,
      1
    ],
    "123": [
      "ifeq",
      1,
      1
    ],
    "124": [
      "15",
      1,
      1
    ],
    "126": [
      "new",
      1,
      0
    ],
    "127": [
      "org/apache/commons/collections4/iterators/NodeListIterator",
      1,
      0
    ],
    "129": [
      "dup",
      1,
      0
    ],
    "130": [
      "aload_0",
      1,
      0
    ],
    "131": [
      "checkcast",
      1,
      0
    ],
    "132": [
      "org/w3c/dom/Node",
      1,
      0
    ],
    "134": [
      "invokespecial",
      1,
      0
    ],
    "135": [
      "org/apache/commons/collections4/iterators/NodeListIterator.<init>:(Lorg/w3c/dom/Node;)V",
      1,
      0
    ],
    "137": [
      "areturn",
      1,
      0
    ],
    "138": [
      "aload_0",
      1,
      1
    ],
    "139": [
      "instanceof",
      1,
      1
    ],
    "140": [
      "java/util/Dictionary",
      1,
      1
    ],
    "142": [
      "ifeq",
      1,
      1
    ],
    "143": [
      "18",
      1,
      1
    ],
    "145": [
      "new",
      1,
      0
    ],
    "146": [
      "org/apache/commons/collections4/iterators/EnumerationIterator",
      1,
      0
    ],
    "148": [
      "dup",
      1,
      0
    ],
    "149": [
      "aload_0",
      1,
      0
    ],
    "150": [
      "checkcast",
      1,
      0
    ],
    "151": [
      "java/util/Dictionary",
      1,
      0
    ],
    "153": [
      "invokevirtual",
      1,
      0
    ],
    "154": [
      "java/util/Dictionary.elements:()Ljava/util/Enumeration;",
      1,
      0
    ],
    "156": [
      "invokespecial",
      1,
      0
    ],
    "157": [
      "org/apache/commons/collections4/iterators/EnumerationIterator.<init>:(Ljava/util/Enumeration;)V",
      1,
      0
    ],
    "159": [
      "areturn",
      1,
      0
    ],
    "160": [
      "aload_0",
      1,
      0
    ],
    "161": [
      "invokevirtual",
      1,
      0
    ],
    "162": [
      "java/lang/Object.getClass:()Ljava/lang/Class;",
      1,
      0
    ],
    "164": [
      "invokevirtual",
      1,
      0
    ],
    "165": [
      "java/lang/Class.isArray:()Z",
      1,
      0
    ],
    "167": [
      "ifeq",
      1,
      0
    ],
    "168": [
      "12",
      1,
      0
    ],
    "170": [
      "new",
      1,
      0
    ],
    "171": [
      "org/apache/commons/collections4/iterators/ArrayIterator",
      1,
      0
    ],
    "173": [
      "dup",
      1,
      0
    ],
    "174": [
      "aload_0",
      1,
      0
    ],
    "175": [
      "invokespecial",
      1,
      0
    ],
    "176": [
      "org/apache/commons/collections4/iterators/ArrayIterator.<init>:(Ljava/lang/Object;)V",
      1,
      0
    ],
    "178": [
      "areturn",
      1,
      0
    ],
    "179": [
      "aload_0",
      0,
      0
    ],
    "180": [
      "invokevirtual",
      0,
      0
    ],
    "181": [
      "java/lang/Object.getClass:()Ljava/lang/Class;",
      0,
      0
    ],
    "183": [
      "ldc",
      0,
      0
    ],
    "184": [
      "iterator",
      0,
      0
    ],
    "185": [
      "aconst_null",
      0,
      0
    ],
    "186": [
      "checkcast",
      0,
      0
    ],
    "187": [
      "[Ljava/lang/Class;",
      0,
      0
    ],
    "189": [
      "invokevirtual",
      0,
      0
    ],
    "190": [
      "java/lang/Class.getMethod:(Ljava/lang/String;[Ljava/lang/Class;)Ljava/lang/reflect/Method;",
      0,
      0
    ],
    "192": [
      "astore_1",
      0,
      0
    ],
    "193": [
      "ldc",
      1,
      1
    ],
    "194": [
      "java/util/Iterator",
      1,
      1
    ],
    "195": [
      "aload_1",
      1,
      1
    ],
    "196": [
      "invokevirtual",
      1,
      1
    ],
    "197": [
      "java/lang/reflect/Method.getReturnType:()Ljava/lang/Class;",
      1,
      1
    ],
    "199": [
      "invokevirtual",
      1,
      1
    ],
    "200": [
      "java/lang/Class.isAssignableFrom:(Ljava/lang/Class;)Z",
      1,
      1
    ],
    "202": [
      "ifeq",
      1,
      1
    ],
    "203": [
      "22",
      1,
      1
    ],
    "205": [
      "aload_1",
      1,
      0
    ],
    "206": [
      "aload_0",
      1,
      0
    ],
    "207": [
      "aconst_null",
      1,
      0
    ],
    "208": [
      "checkcast",
      1,
      0
    ],
    "209": [
      "[Ljava/lang/Object;",
      1,
      0
    ],
    "211": [
      "invokevirtual",
      1,
      0
    ],
    "212": [
      "java/lang/reflect/Method.invoke:(Ljava/lang/Object;[Ljava/lang/Object;)Ljava/lang/Object;",
      1,
      0
    ],
    "214": [
      "checkcast",
      1,
      0
    ],
    "215": [
      "java/util/Iterator",
      1,
      0
    ],
    "217": [
      "astore_2",
      1,
      0
    ],
    "218": [
      "aload_2",
      2,
      1
    ],
    "219": [
      "ifnull",
      2,
      1
    ],
    "220": [
      "5",
      2,
      1
    ],
    "222": [
      "aload_2",
      2,
      0
    ],
    "223": [
      "areturn",
      2,
      0
    ],
    "224": [
      "goto",
      0,
      0
    ],
    "225": [
      "16",
      0,
      0
    ],
    "227": [
      "astore_1",
      0,
      0
    ],
    "228": [
      "goto",
      0,
      0
    ],
    "229": [
      "12",
      0,
      0
    ],
    "231": [
      "astore_1",
      0,
      0
    ],
    "232": [
      "goto",
      0,
      0
    ],
    "233": [
      "8",
      0,
      0
    ],
    "235": [
      "astore_1",
      0,
      0
    ],
    "236": [
      "goto",
      0,
      0
    ],
    "237": [
      "4",
      0,
      0
    ],
    "239": [
      "astore_1",
      0,
      0
    ],
    "240": [
      "aload_0",
      0,
      0
    ],
    "241": [
      "invokestatic",
      0,
      0
    ],
    "242": [
      "org/apache/commons/collections4/IteratorUtils.singletonIterator:(Ljava/lang/Object;)Lorg/apache/commons/collections4/ResettableIterator;",
      0,
      0
    ],
    "244": [
      "areturn",
      0,
      0
    ]
  },
  "forEach": {
    "0": [
      "aload_1",
      1,
      1
    ],
    "1": [
      "ifnonnull",
      1,
      1
    ],
    "2": [
      "13",
      1,
      1
    ],
    "4": [
      "new",
      1,
      0
    ],
    "5": [
      "java/lang/NullPointerException",
      1,
      0
    ],
    "7": [
      "dup",
      1,
      0
    ],
    "8": [
      "ldc",
      1,
      0
    ],
    "9": [
      "Closure must not be null",
      1,
      0
    ],
    "10": [
      "invokespecial",
      1,
      0
    ],
    "11": [
      "java/lang/NullPointerException.<init>:(Ljava/lang/String;)V",
      1,
      0
    ],
    "13": [
      "athrow",
      1,
      0
    ],
    "14": [
      "aload_0",
      1,
      1
    ],
    "15": [
      "ifnull",
      1,
      1
    ],
    "16": [
      "29",
      1,
      1
    ],
    "18": [
      "aload_0",
      2,
      3
    ],
    "19": [
      "invokeinterface",
      2,
      3
    ],
    "20": [
      "java/util/Iterator.next:()Ljava/lang/Object;",
      2,
      3
    ],
    "22": [
      "0",
      2,
      3
    ],
    "24": [
      "ifeq",
      2,
      3
    ],
    "25": [
      "20",
      2,
      3
    ],
    "27": [
      "aload_0",
      2,
      0
    ],
    "28": [
      "invokeinterface",
      2,
      0
    ],
    "29": [
      "java/util/Iterator.add:(Ljava/lang/Object;)Z",
      2,
      0
    ],
    "31": [
      "0",
      2,
      0
    ],
    "33": [
      "astore_2",
      2,
      0
    ],
    "34": [
      "aload_1",
      2,
      0
    ],
    "35": [
      "aload_2",
      2,
      0
    ],
    "36": [
      "invokeinterface",
      2,
      0
    ],
    "37": [
      "org/apache/commons/collections4/Closure.Closure must not be null.",
      2,
      0
    ],
    "39": [
      "0",
      2,
      0
    ],
    "41": [
      "goto",
      1,
      3
    ],
    "42": [
      "-23",
      1,
      3
    ],
    "44": [
      "return",
      0,
      0
    ]
  },
  "forEachButLast": {
    "0": [
      "aload_1",
      1,
      1
    ],
    "1": [
      "ifnonnull",
      1,
      1
    ],
    "2": [
      "13",
      1,
      1
    ],
    "4": [
      "new",
      1,
      0
    ],
    "5": [
      "java/lang/NullPointerException",
      1,
      0
    ],
    "7": [
      "dup",
      1,
      0
    ],
    "8": [
      "ldc",
      1,
      0
    ],
    "9": [
      "Closure must not be null.",
      1,
      0
    ],
    "10": [
      "invokespecial",
      1,
      0
    ],
    "11": [
      "java/lang/NullPointerException.<init>:(Ljava/lang/String;)V",
      1,
      0
    ],
    "13": [
      "athrow",
      1,
      0
    ],
    "14": [
      "aload_0",
      1,
      1
    ],
    "15": [
      "ifnull",
      1,
      1
    ],
    "16": [
      "43",
      1,
      1
    ],
    "18": [
      "aload_0",
      2,
      3
    ],
    "19": [
      "invokeinterface",
      2,
      3
    ],
    "20": [
      "java/util/Iterator.next:()Ljava/lang/Object;",
      2,
      3
    ],
    "22": [
      "0",
      2,
      3
    ],
    "24": [
      "ifeq",
      2,
      3
    ],
    "25": [
      "34",
      2,
      3
    ],
    "27": [
      "aload_0",
      2,
      0
    ],
    "28": [
      "invokeinterface",
      2,
      0
    ],
    "29": [
      "java/util/Iterator.add:(Ljava/lang/Object;)Z",
      2,
      0
    ],
    "31": [
      "0",
      2,
      0
    ],
    "33": [
      "astore_2",
      2,
      0
    ],
    "34": [
      "aload_0",
      3,
      1
    ],
    "35": [
      "invokeinterface",
      3,
      1
    ],
    "36": [
      "java/util/Iterator.next:()Ljava/lang/Object;",
      3,
      1
    ],
    "38": [
      "0",
      3,
      1
    ],
    "40": [
      "ifeq",
      3,
      1
    ],
    "41": [
      "13",
      3,
      1
    ],
    "43": [
      "aload_1",
      3,
      0
    ],
    "44": [
      "aload_2",
      3,
      0
    ],
    "45": [
      "invokeinterface",
      3,
      0
    ],
    "46": [
      "org/apache/commons/collections4/Closure.Closure must not be null.",
      3,
      0
    ],
    "48": [
      "0",
      3,
      0
    ],
    "50": [
      "goto",
      3,
      0
    ],
    "51": [
      "5",
      3,
      0
    ],
    "53": [
      "aload_2",
      4,
      0
    ],
    "54": [
      "areturn",
      4,
      0
    ],
    "55": [
      "goto",
      1,
      3
    ],
    "56": [
      "-37",
      1,
      3
    ],
    "58": [
      "aconst_null",
      0,
      0
    ],
    "59": [
      "areturn",
      0,
      0
    ]
  },
  "find": {
    "0": [
      "aload_1",
      1,
      1
    ],
    "1": [
      "ifnonnull",
      1,
      1
    ],
    "2": [
      "13",
      1,
      1
    ],
    "4": [
      "new",
      1,
      0
    ],
    "5": [
      "java/lang/NullPointerException",
      1,
      0
    ],
    "7": [
      "dup",
      1,
      0
    ],
    "8": [
      "ldc",
      1,
      0
    ],
    "9": [
      "Predicate must not be null",
      1,
      0
    ],
    "10": [
      "invokespecial",
      1,
      0
    ],
    "11": [
      "java/lang/NullPointerException.<init>:(Ljava/lang/String;)V",
      1,
      0
    ],
    "13": [
      "athrow",
      1,
      0
    ],
    "14": [
      "aload_0",
      1,
      1
    ],
    "15": [
      "ifnull",
      1,
      1
    ],
    "16": [
      "34",
      1,
      1
    ],
    "18": [
      "aload_0",
      2,
      3
    ],
    "19": [
      "invokeinterface",
      2,
      3
    ],
    "20": [
      "java/util/Iterator.next:()Ljava/lang/Object;",
      2,
      3
    ],
    "22": [
      "0",
      2,
      3
    ],
    "24": [
      "ifeq",
      2,
      3
    ],
    "25": [
      "25",
      2,
      3
    ],
    "27": [
      "aload_0",
      2,
      0
    ],
    "28": [
      "invokeinterface",
      2,
      0
    ],
    "29": [
      "java/util/Iterator.add:(Ljava/lang/Object;)Z",
      2,
      0
    ],
    "31": [
      "0",
      2,
      0
    ],
    "33": [
      "astore_2",
      2,
      0
    ],
    "34": [
      "aload_1",
      3,
      1
    ],
    "35": [
      "aload_2",
      3,
      1
    ],
    "36": [
      "invokeinterface",
      3,
      1
    ],
    "37": [
      "org/apache/commons/collections4/Predicate.indexOf:(Ljava/util/Iterator;Lorg/apache/commons/collections4/Predicate;)I",
      3,
      1
    ],
    "39": [
      "0",
      3,
      1
    ],
    "41": [
      "ifeq",
      3,
      1
    ],
    "42": [
      "5",
      3,
      1
    ],
    "44": [
      "aload_2",
      3,
      0
    ],
    "45": [
      "areturn",
      3,
      0
    ],
    "46": [
      "goto",
      1,
      3
    ],
    "47": [
      "-28",
      1,
      3
    ],
    "49": [
      "aconst_null",
      0,
      0
    ],
    "50": [
      "areturn",
      0,
      0
    ]
  },
  "indexOf": {
    "0": [
      "aload_1",
      1,
      1
    ],
    "1": [
      "ifnonnull",
      1,
      1
    ],
    "2": [
      "13",
      1,
      1
    ],
    "4": [
      "new",
      1,
      0
    ],
    "5": [
      "java/lang/NullPointerException",
      1,
      0
    ],
    "7": [
      "dup",
      1,
      0
    ],
    "8": [
      "ldc",
      1,
      0
    ],
    "9": [
      "Predicate must not be null",
      1,
      0
    ],
    "10": [
      "invokespecial",
      1,
      0
    ],
    "11": [
      "java/lang/NullPointerException.<init>:(Ljava/lang/String;)V",
      1,
      0
    ],
    "13": [
      "athrow",
      1,
      0
    ],
    "14": [
      "aload_0",
      1,
      1
    ],
    "15": [
      "ifnull",
      1,
      1
    ],
    "16": [
      "39",
      1,
      1
    ],
    "18": [
      "iconst_0",
      2,
      4
    ],
    "19": [
      "istore_2",
      2,
      4
    ],
    "20": [
      "aload_0",
      2,
      4
    ],
    "21": [
      "invokeinterface",
      2,
      4
    ],
    "22": [
      "java/util/Iterator.next:()Ljava/lang/Object;",
      2,
      4
    ],
    "24": [
      "0",
      2,
      4
    ],
    "26": [
      "ifeq",
      2,
      4
    ],
    "27": [
      "28",
      2,
      4
    ],
    "29": [
      "aload_0",
      2,
      0
    ],
    "30": [
      "invokeinterface",
      2,
      0
    ],
    "31": [
      "java/util/Iterator.add:(Ljava/lang/Object;)Z",
      2,
      0
    ],
    "33": [
      "0",
      2,
      0
    ],
    "35": [
      "astore_3",
      2,
      0
    ],
    "36": [
      "aload_1",
      3,
      1
    ],
    "37": [
      "aload_3",
      3,
      1
    ],
    "38": [
      "invokeinterface",
      3,
      1
    ],
    "39": [
      "org/apache/commons/collections4/Predicate.indexOf:(Ljava/util/Iterator;Lorg/apache/commons/collections4/Predicate;)I",
      3,
      1
    ],
    "41": [
      "0",
      3,
      1
    ],
    "43": [
      "ifeq",
      3,
      1
    ],
    "44": [
      "5",
      3,
      1
    ],
    "46": [
      "iload_2",
      3,
      0
    ],
    "47": [
      "ireturn",
      3,
      0
    ],
    "48": [
      "iinc",
      3,
      0
    ],
    "49": [
      "#2",
      3,
      0
    ],
    "50": [
      "-89",
      3,
      0
    ],
    "51": [
      "goto",
      3,
      4
    ],
    "52": [
      "-31",
      3,
      4
    ],
    "54": [
      "iconst_m1",
      1,
      0
    ],
    "55": [
      "ireturn",
      1,
      0
    ]
  },
  "matchesAny": {
    "0": [
      "aload_0",
      0,
      0
    ],
    "1": [
      "aload_1",
      0,
      0
    ],
    "2": [
      "invokestatic",
      0,
      0
    ],
    "3": [
      "org/apache/commons/collections4/IteratorUtils.indexOf:(Ljava/util/Iterator;Lorg/apache/commons/collections4/Predicate;)I",
      0,
      0
    ],
    "5": [
      "iconst_m1",
      0,
      0
    ],
    "6": [
      "if_icmpeq",
      0,
      0
    ],
    "7": [
      "7",
      0,
      0
    ],
    "9": [
      "iconst_1",
      0,
      0
    ],
    "10": [
      "goto",
      0,
      0
    ],
    "11": [
      "4",
      0,
      0
    ],
    "13": [
      "iconst_0",
      0,
      0
    ],
    "14": [
      "ireturn",
      0,
      0
    ]
  },
  "matchesAll": {
    "0": [
      "aload_1",
      1,
      1
    ],
    "1": [
      "ifnonnull",
      1,
      1
    ],
    "2": [
      "13",
      1,
      1
    ],
    "4": [
      "new",
      1,
      0
    ],
    "5": [
      "java/lang/NullPointerException",
      1,
      0
    ],
    "7": [
      "dup",
      1,
      0
    ],
    "8": [
      "ldc",
      1,
      0
    ],
    "9": [
      "Predicate must not be null",
      1,
      0
    ],
    "10": [
      "invokespecial",
      1,
      0
    ],
    "11": [
      "java/lang/NullPointerException.<init>:(Ljava/lang/String;)V",
      1,
      0
    ],
    "13": [
      "athrow",
      1,
      0
    ],
    "14": [
      "aload_0",
      1,
      1
    ],
    "15": [
      "ifnull",
      1,
      1
    ],
    "16": [
      "34",
      1,
      1
    ],
    "18": [
      "aload_0",
      2,
      3
    ],
    "19": [
      "invokeinterface",
      2,
      3
    ],
    "20": [
      "java/util/Iterator.next:()Ljava/lang/Object;",
      2,
      3
    ],
    "22": [
      "0",
      2,
      3
    ],
    "24": [
      "ifeq",
      2,
      3
    ],
    "25": [
      "25",
      2,
      3
    ],
    "27": [
      "aload_0",
      2,
      0
    ],
    "28": [
      "invokeinterface",
      2,
      0
    ],
    "29": [
      "java/util/Iterator.add:(Ljava/lang/Object;)Z",
      2,
      0
    ],
    "31": [
      "0",
      2,
      0
    ],
    "33": [
      "astore_2",
      2,
      0
    ],
    "34": [
      "aload_1",
      3,
      1
    ],
    "35": [
      "aload_2",
      3,
      1
    ],
    "36": [
      "invokeinterface",
      3,
      1
    ],
    "37": [
      "org/apache/commons/collections4/Predicate.indexOf:(Ljava/util/Iterator;Lorg/apache/commons/collections4/Predicate;)I",
      3,
      1
    ],
    "39": [
      "0",
      3,
      1
    ],
    "41": [
      "ifne",
      3,
      1
    ],
    "42": [
      "5",
      3,
      1
    ],
    "44": [
      "iconst_0",
      3,
      0
    ],
    "45": [
      "ireturn",
      3,
      0
    ],
    "46": [
      "goto",
      1,
      3
    ],
    "47": [
      "-28",
      1,
      3
    ],
    "49": [
      "iconst_1",
      0,
      0
    ],
    "50": [
      "ireturn",
      0,
      0
    ]
  },
  "isEmpty": {
    "0": [
      "aload_0",
      0,
      0
    ],
    "1": [
      "ifnull",
      0,
      0
    ],
    "2": [
      "12",
      0,
      0
    ],
    "4": [
      "aload_0",
      0,
      0
    ],
    "5": [
      "invokeinterface",
      0,
      0
    ],
    "6": [
      "java/util/Iterator.next:()Ljava/lang/Object;",
      0,
      0
    ],
    "8": [
      "0",
      0,
      0
    ],
    "10": [
      "ifne",
      0,
      0
    ],
    "11": [
      "7",
      0,
      0
    ],
    "13": [
      "iconst_1",
      0,
      0
    ],
    "14": [
      "goto",
      0,
      0
    ],
    "15": [
      "4",
      0,
      0
    ],
    "17": [
      "iconst_0",
      0,
      0
    ],
    "18": [
      "ireturn",
      0,
      0
    ]
  },
  "contains": {
    "0": [
      "aload_0",
      0,
      0
    ],
    "1": [
      "aload_1",
      0,
      0
    ],
    "2": [
      "invokestatic",
      0,
      0
    ],
    "3": [
      "org/apache/commons/collections4/functors/EqualPredicate.equalPredicate:(Ljava/lang/Object;)Lorg/apache/commons/collections4/Predicate;",
      0,
      0
    ],
    "5": [
      "invokestatic",
      0,
      0
    ],
    "6": [
      "org/apache/commons/collections4/IteratorUtils.matchesAny:(Ljava/util/Iterator;Lorg/apache/commons/collections4/Predicate;)Z",
      0,
      0
    ],
    "8": [
      "ireturn",
      0,
      0
    ]
  },
  "get": {
    "0": [
      "iload_1",
      0,
      0
    ],
    "1": [
      "istore_2",
      0,
      0
    ],
    "2": [
      "iload_2",
      0,
      0
    ],
    "3": [
      "invokestatic",
      0,
      0
    ],
    "4": [
      "org/apache/commons/collections4/CollectionUtils.checkIndexBounds:(I)V",
      0,
      0
    ],
    "6": [
      "aload_0",
      1,
      3
    ],
    "7": [
      "invokeinterface",
      1,
      3
    ],
    "8": [
      "java/util/Iterator.next:()Ljava/lang/Object;",
      1,
      3
    ],
    "10": [
      "0",
      1,
      3
    ],
    "12": [
      "ifeq",
      1,
      3
    ],
    "13": [
      "28",
      1,
      3
    ],
    "15": [
      "iinc",
      1,
      0
    ],
    "16": [
      "#2",
      1,
      0
    ],
    "17": [
      "28",
      1,
      0
    ],
    "18": [
      "iload_2",
      2,
      1
    ],
    "19": [
      "iconst_m1",
      2,
      1
    ],
    "20": [
      "if_icmpne",
      2,
      1
    ],
    "21": [
      "10",
      2,
      1
    ],
    "23": [
      "aload_0",
      2,
      0
    ],
    "24": [
      "invokeinterface",
      2,
      0
    ],
    "25": [
      "java/util/Iterator.add:(Ljava/lang/Object;)Z",
      2,
      0
    ],
    "27": [
      "0",
      2,
      0
    ],
    "29": [
      "areturn",
      2,
      0
    ],
    "30": [
      "aload_0",
      1,
      0
    ],
    "31": [
      "invokeinterface",
      1,
      0
    ],
    "32": [
      "java/util/Iterator.add:(Ljava/lang/Object;)Z",
      1,
      0
    ],
    "34": [
      "0",
      1,
      0
    ],
    "36": [
      "pop",
      1,
      0
    ],
    "37": [
      "goto",
      1,
      3
    ],
    "38": [
      "-31",
      1,
      3
    ],
    "40": [
      "new",
      0,
      0
    ],
    "41": [
      "java/lang/IndexOutOfBoundsException",
      0,
      0
    ],
    "43": [
      "dup",
      0,
      0
    ],
    "44": [
      "new",
      0,
      0
    ],
    "45": [
      "java/lang/StringBuilder",
      0,
      0
    ],
    "47": [
      "dup",
      0,
      0
    ],
    "48": [
      "invokespecial",
      0,
      0
    ],
    "49": [
      "java/lang/StringBuilder.<init>:()V",
      0,
      0
    ],
    "51": [
      "ldc",
      0,
      0
    ],
    "52": [
      "Entry does not exist: ",
      0,
      0
    ],
    "53": [
      "invokevirtual",
      0,
      0
    ],
    "54": [
      "java/lang/StringBuilder.append:(Ljava/lang/String;)Ljava/lang/StringBuilder;",
      0,
      0
    ],
    "56": [
      "iload_2",
      0,
      0
    ],
    "57": [
      "invokevirtual",
      0,
      0
    ],
    "58": [
      "java/lang/StringBuilder.append:(I)Ljava/lang/StringBuilder;",
      0,
      0
    ],
    "60": [
      "invokevirtual",
      0,
      0
    ],
    "61": [
      "java/lang/StringBuilder.toString:()Ljava/lang/String;",
      0,
      0
    ],
    "63": [
      "invokespecial",
      0,
      0
    ],
    "64": [
      "java/lang/IndexOutOfBoundsException.<init>:(Ljava/lang/String;)V",
      0,
      0
    ],
    "66": [
      "athrow",
      0,
      0
    ]
  },
  "size": {
    "0": [
      "iconst_0",
      0,
      0
    ],
    "1": [
      "istore_1",
      0,
      0
    ],
    "2": [
      "aload_0",
      1,
      1
    ],
    "3": [
      "ifnull",
      1,
      1
    ],
    "4": [
      "25",
      1,
      1
    ],
    "6": [
      "aload_0",
      2,
      3
    ],
    "7": [
      "invokeinterface",
      2,
      3
    ],
    "8": [
      "java/util/Iterator.next:()Ljava/lang/Object;",
      2,
      3
    ],
    "10": [
      "0",
      2,
      3
    ],
    "12": [
      "ifeq",
      2,
      3
    ],
    "13": [
      "16",
      2,
      3
    ],
    "15": [
      "aload_0",
      2,
      0
    ],
    "16": [
      "invokeinterface",
      2,
      0
    ],
    "17": [
      "java/util/Iterator.add:(Ljava/lang/Object;)Z",
      2,
      0
    ],
    "19": [
      "0",
      2,
      0
    ],
    "21": [
      "pop",
      2,
      0
    ],
    "22": [
      "iinc",
      2,
      0
    ],
    "23": [
      "#1",
      2,
      0
    ],
    "24": [
      "-89",
      2,
      0
    ],
    "25": [
      "goto",
      2,
      3
    ],
    "26": [
      "-19",
      2,
      3
    ],
    "28": [
      "iload_1",
      0,
      0
    ],
    "29": [
      "ireturn",
      0,
      0
    ]
  },
  "toString": {
    "0": [
      "aload_1",
      1,
      1
    ],
    "1": [
      "ifnonnull",
      1,
      1
    ],
    "2": [
      "13",
      1,
      1
    ],
    "4": [
      "new",
      1,
      0
    ],
    "5": [
      "java/lang/NullPointerException",
      1,
      0
    ],
    "7": [
      "dup",
      1,
      0
    ],
    "8": [
      "ldc",
      1,
      0
    ],
    "9": [
      "transformer may not be null",
      1,
      0
    ],
    "10": [
      "invokespecial",
      1,
      0
    ],
    "11": [
      "java/lang/NullPointerException.<init>:(Ljava/lang/String;)V",
      1,
      0
    ],
    "13": [
      "athrow",
      1,
      0
    ],
    "14": [
      "aload_2",
      1,
      1
    ],
    "15": [
      "ifnonnull",
      1,
      1
    ],
    "16": [
      "13",
      1,
      1
    ],
    "18": [
      "new",
      1,
      0
    ],
    "19": [
      "java/lang/NullPointerException",
      1,
      0
    ],
    "21": [
      "dup",
      1,
      0
    ],
    "22": [
      "ldc",
      1,
      0
    ],
    "23": [
      "delimiter may not be null",
      1,
      0
    ],
    "24": [
      "invokespecial",
      1,
      0
    ],
    "25": [
      "java/lang/NullPointerException.<init>:(Ljava/lang/String;)V",
      1,
      0
    ],
    "27": [
      "athrow",
      1,
      0
    ],
    "28": [
      "aload_3",
      1,
      1
    ],
    "29": [
      "ifnonnull",
      1,
      1
    ],
    "30": [
      "13",
      1,
      1
    ],
    "32": [
      "new",
      1,
      0
    ],
    "33": [
      "java/lang/NullPointerException",
      1,
      0
    ],
    "35": [
      "dup",
      1,
      0
    ],
    "36": [
      "ldc",
      1,
      0
    ],
    "37": [
      "prefix may not be null",
      1,
      0
    ],
    "38": [
      "invokespecial",
      1,
      0
    ],
    "39": [
      "java/lang/NullPointerException.<init>:(Ljava/lang/String;)V",
      1,
      0
    ],
    "41": [
      "athrow",
      1,
      0
    ],
    "42": [
      "aload",
      1,
      1
    ],
    "43": [
      "#4",
      1,
      1
    ],
    "44": [
      "ifnonnull",
      1,
      1
    ],
    "45": [
      "13",
      1,
      1
    ],
    "47": [
      "new",
      1,
      0
    ],
    "48": [
      "java/lang/NullPointerException",
      1,
      0
    ],
    "50": [
      "dup",
      1,
      0
    ],
    "51": [
      "ldc",
      1,
      0
    ],
    "52": [
      "suffix may not be null",
      1,
      0
    ],
    "53": [
      "invokespecial",
      1,
      0
    ],
    "54": [
      "java/lang/NullPointerException.<init>:(Ljava/lang/String;)V",
      1,
      0
    ],
    "56": [
      "athrow",
      1,
      0
    ],
    "57": [
      "new",
      0,
      0
    ],
    "58": [
      "java/lang/StringBuilder",
      0,
      0
    ],
    "60": [
      "dup",
      0,
      0
    ],
    "61": [
      "aload_3",
      0,
      0
    ],
    "62": [
      "invokespecial",
      0,
      0
    ],
    "63": [
      "java/lang/StringBuilder.<init>:(Ljava/lang/String;)V",
      0,
      0
    ],
    "65": [
      "astore",
      0,
      0
    ],
    "66": [
      "#5",
      0,
      0
    ],
    "67": [
      "aload_0",
      1,
      1
    ],
    "68": [
      "ifnull",
      1,
      1
    ],
    "69": [
      "74",
      1,
      1
    ],
    "71": [
      "aload_0",
      2,
      3
    ],
    "72": [
      "invokeinterface",
      2,
      3
    ],
    "73": [
      "java/util/Iterator.next:()Ljava/lang/Object;",
      2,
      3
    ],
    "75": [
      "0",
      2,
      3
    ],
    "77": [
      "ifeq",
      2,
      3
    ],
    "78": [
      "38",
      2,
      3
    ],
    "80": [
      "aload_0",
      2,
      0
    ],
    "81": [
      "invokeinterface",
      2,
      0
    ],
    "82": [
      "java/util/Iterator.add:(Ljava/lang/Object;)Z",
      2,
      0
    ],
    "84": [
      "0",
      2,
      0
    ],
    "86": [
      "astore",
      2,
      0
    ],
    "87": [
      "#6",
      2,
      0
    ],
    "88": [
      "aload",
      2,
      0
    ],
    "89": [
      "#5",
      2,
      0
    ],
    "90": [
      "aload_1",
      2,
      0
    ],
    "91": [
      "aload",
      2,
      0
    ],
    "92": [
      "#6",
      2,
      0
    ],
    "93": [
      "invokeinterface",
      2,
      0
    ],
    "94": [
      "org/apache/commons/collections4/Transformer.java/lang/String",
      2,
      0
    ],
    "96": [
      "0",
      2,
      0
    ],
    "98": [
      "checkcast",
      2,
      0
    ],
    "99": [
      "java/lang/String",
      2,
      0
    ],
    "101": [
      "invokevirtual",
      2,
      0
    ],
    "102": [
      "java/lang/StringBuilder.append:(Ljava/lang/String;)Ljava/lang/StringBuilder;",
      2,
      0
    ],
    "104": [
      "pop",
      2,
      0
    ],
    "105": [
      "aload",
      2,
      0
    ],
    "106": [
      "#5",
      2,
      0
    ],
    "107": [
      "aload_2",
      2,
      0
    ],
    "108": [
      "invokevirtual",
      2,
      0
    ],
    "109": [
      "java/lang/StringBuilder.append:(Ljava/lang/String;)Ljava/lang/StringBuilder;",
      2,
      0
    ],
    "111": [
      "pop",
      2,
      0
    ],
    "112": [
      "goto",
      1,
      3
    ],
    "113": [
      "-41",
      1,
      3
    ],
    "115": [
      "aload",
      1,
      0
    ],
    "116": [
      "#5",
      1,
      0
    ],
    "117": [
      "invokevirtual",
      1,
      0
    ],
    "118": [
      "java/lang/StringBuilder.length:()I",
      1,
      0
    ],
    "120": [
      "aload_3",
      1,
      0
    ],
    "121": [
      "invokevirtual",
      1,
      0
    ],
    "122": [
      "java/lang/String.length:()I",
      1,
      0
    ],
    "124": [
      "if_icmple",
      1,
      0
    ],
    "125": [
      "18",
      1,
      0
    ],
    "127": [
      "aload",
      1,
      0
    ],
    "128": [
      "#5",
      1,
      0
    ],
    "129": [
      "aload",
      1,
      0
    ],
    "130": [
      "#5",
      1,
      0
    ],
    "131": [
      "invokevirtual",
      1,
      0
    ],
    "132": [
      "java/lang/StringBuilder.length:()I",
      1,
      0
    ],
    "134": [
      "aload_2",
      1,
      0
    ],
    "135": [
      "invokevirtual",
      1,
      0
    ],
    "136": [
      "java/lang/String.length:()I",
      1,
      0
    ],
    "138": [
      "isub",
      1,
      0
    ],
    "139": [
      "invokevirtual",
      1,
      0
    ],
    "140": [
      "java/lang/StringBuilder.setLength:(I)V",
      1,
      0
    ],
    "142": [
      "aload",
      0,
      0
    ],
    "143": [
      "#5",
      0,
      0
    ],
    "144": [
      "aload",
      0,
      0
    ],
    "145": [
      "#4",
      0,
      0
    ],
    "146": [
      "invokevirtual",
      0,
      0
    ],
    "147": [
      "java/lang/StringBuilder.append:(Ljava/lang/String;)Ljava/lang/StringBuilder;",
      0,
      0
    ],
    "149": [
      "pop",
      0,
      0
    ],
    "150": [
      "aload",
      0,
      0
    ],
    "151": [
      "#5",
      0,
      0
    ],
    "152": [
      "invokevirtual",
      0,
      0
    ],
    "153": [
      "java/lang/StringBuilder.toString:()Ljava/lang/String;",
      0,
      0
    ],
    "155": [
      "areturn",
      0,
      0
    ]
  },
  "<clinit>": {
    "0": [
      "getstatic",
      0,
      0
    ],
    "1": [
      "org/apache/commons/collections4/iterators/EmptyIterator.RESETTABLE_INSTANCE:Lorg/apache/commons/collections4/ResettableIterator;",
      0,
      0
    ],
    "3": [
      "putstatic",
      0,
      0
    ],
    "4": [
      "org/apache/commons/collections4/IteratorUtils.EMPTY_ITERATOR:Lorg/apache/commons/collections4/ResettableIterator;",
      0,
      0
    ],
    "6": [
      "getstatic",
      0,
      0
    ],
    "7": [
      "org/apache/commons/collections4/iterators/EmptyListIterator.RESETTABLE_INSTANCE:Lorg/apache/commons/collections4/ResettableListIterator;",
      0,
      0
    ],
    "9": [
      "putstatic",
      0,
      0
    ],
    "10": [
      "org/apache/commons/collections4/IteratorUtils.EMPTY_LIST_ITERATOR:Lorg/apache/commons/collections4/ResettableListIterator;",
      0,
      0
    ],
    "12": [
      "getstatic",
      0,
      0
    ],
    "13": [
      "org/apache/commons/collections4/iterators/EmptyOrderedIterator.INSTANCE:Lorg/apache/commons/collections4/OrderedIterator;",
      0,
      0
    ],
    "15": [
      "putstatic",
      0,
      0
    ],
    "16": [
      "org/apache/commons/collections4/IteratorUtils.EMPTY_ORDERED_ITERATOR:Lorg/apache/commons/collections4/OrderedIterator;",
      0,
      0
    ],
    "18": [
      "getstatic",
      0,
      0
    ],
    "19": [
      "org/apache/commons/collections4/iterators/EmptyMapIterator.INSTANCE:Lorg/apache/commons/collections4/MapIterator;",
      0,
      0
    ],
    "21": [
      "putstatic",
      0,
      0
    ],
    "22": [
      "org/apache/commons/collections4/IteratorUtils.EMPTY_MAP_ITERATOR:Lorg/apache/commons/collections4/MapIterator;",
      0,
      0
    ],
    "24": [
      "getstatic",
      0,
      0
    ],
    "25": [
      "org/apache/commons/collections4/iterators/EmptyOrderedMapIterator.INSTANCE:Lorg/apache/commons/collections4/OrderedMapIterator;",
      0,
      0
    ],
    "27": [
      "putstatic",
      0,
      0
    ],
    "28": [
      "org/apache/commons/collections4/IteratorUtils.EMPTY_ORDERED_MAP_ITERATOR:Lorg/apache/commons/collections4/OrderedMapIterator;",
      0,
      0
    ],
    "30": [
      "return",
      0,
      0
    ]
  }
}