{
  "doIntegrate": {
    "LocalVariableDeclaration": [
      [
        "6",
        "iconst_2"
      ],
      [
        "7",
        "istore_3"
      ]
    ],
    "WhileStatement": [
      [
        "8",
        "aload_0"
      ],
      [
        "9",
        "iload_3"
      ],
      [
        "10",
        "invokespecial"
      ],
      [
        "11",
        "org/apache/commons/math3/analysis/integration/IterativeLegendreGaussIntegrator.stage:(I)D"
      ],
      [
        "13",
        "dstore"
      ],
      [
        "14",
        "#4"
      ],
      [
        "15",
        "dload"
      ],
      [
        "16",
        "#4"
      ],
      [
        "17",
        "dload_1"
      ],
      [
        "18",
        "dsub"
      ],
      [
        "19",
        "invokestatic"
      ],
      [
        "20",
        "org/apache/commons/math3/util/FastMath.abs:(D)D"
      ],
      [
        "22",
        "dstore"
      ],
      [
        "23",
        "#6"
      ],
      [
        "24",
        "aload_0"
      ],
      [
        "25",
        "invokevirtual"
      ],
      [
        "26",
        "org/apache/commons/math3/analysis/integration/IterativeLegendreGaussIntegrator.getAbsoluteAccuracy:()D"
      ],
      [
        "28",
        "aload_0"
      ],
      [
        "29",
        "invokevirtual"
      ],
      [
        "30",
        "org/apache/commons/math3/analysis/integration/IterativeLegendreGaussIntegrator.getRelativeAccuracy:()D"
      ],
      [
        "32",
        "dload_1"
      ],
      [
        "33",
        "invokestatic"
      ],
      [
        "34",
        "org/apache/commons/math3/util/FastMath.abs:(D)D"
      ],
      [
        "36",
        "dload"
      ],
      [
        "37",
        "#4"
      ],
      [
        "38",
        "invokestatic"
      ],
      [
        "39",
        "org/apache/commons/math3/util/FastMath.abs:(D)D"
      ],
      [
        "41",
        "dadd"
      ],
      [
        "42",
        "dmul"
      ],
      [
        "43",
        "ldc2_w"
      ],
      [
        "44",
        "0.5"
      ],
      [
        "46",
        "dmul"
      ],
      [
        "47",
        "invokestatic"
      ],
      [
        "48",
        "org/apache/commons/math3/util/FastMath.max:(DD)D"
      ],
      [
        "50",
        "dstore"
      ],
      [
        "51",
        "#8"
      ],
      [
        "52",
        "aload_0"
      ],
      [
        "53",
        "invokevirtual"
      ],
      [
        "54",
        "org/apache/commons/math3/analysis/integration/IterativeLegendreGaussIntegrator.getIterations:()I"
      ],
      [
        "56",
        "iconst_1"
      ],
      [
        "57",
        "iadd"
      ],
      [
        "58",
        "aload_0"
      ],
      [
        "59",
        "invokevirtual"
      ],
      [
        "60",
        "org/apache/commons/math3/analysis/integration/IterativeLegendreGaussIntegrator.getMinimalIterationCount:()I"
      ],
      [
        "62",
        "if_icmplt"
      ],
      [
        "63",
        "14"
      ],
      [
        "65",
        "dload"
      ],
      [
        "66",
        "#6"
      ],
      [
        "67",
        "dload"
      ],
      [
        "68",
        "#8"
      ],
      [
        "69",
        "dcmpg"
      ],
      [
        "70",
        "ifgt"
      ],
      [
        "71",
        "6"
      ],
      [
        "73",
        "dload"
      ],
      [
        "74",
        "#4"
      ],
      [
        "75",
        "dreturn"
      ],
      [
        "76",
        "ldc2_w"
      ],
      [
        "77",
        "4.0"
      ],
      [
        "79",
        "dload"
      ],
      [
        "80",
        "#6"
      ],
      [
        "81",
        "dload"
      ],
      [
        "82",
        "#8"
      ],
      [
        "83",
        "ddiv"
      ],
      [
        "84",
        "ldc2_w"
      ],
      [
        "85",
        "0.5"
      ],
      [
        "87",
        "aload_0"
      ],
      [
        "88",
        "getfield"
      ],
      [
        "89",
        "org/apache/commons/math3/analysis/integration/IterativeLegendreGaussIntegrator.numberOfPoints:I"
      ],
      [
        "91",
        "i2d"
      ],
      [
        "92",
        "ddiv"
      ],
      [
        "93",
        "invokestatic"
      ],
      [
        "94",
        "org/apache/commons/math3/util/FastMath.pow:(DD)D"
      ],
      [
        "96",
        "invokestatic"
      ],
      [
        "97",
        "org/apache/commons/math3/util/FastMath.min:(DD)D"
      ],
      [
        "99",
        "dstore"
      ],
      [
        "100",
        "#10"
      ],
      [
        "101",
        "dload"
      ],
      [
        "102",
        "#10"
      ],
      [
        "103",
        "iload_3"
      ],
      [
        "104",
        "i2d"
      ],
      [
        "105",
        "dmul"
      ],
      [
        "106",
        "d2i"
      ],
      [
        "107",
        "iload_3"
      ],
      [
        "108",
        "iconst_1"
      ],
      [
        "109",
        "iadd"
      ],
      [
        "110",
        "invokestatic"
      ],
      [
        "111",
        "org/apache/commons/math3/util/FastMath.max:(II)I"
      ],
      [
        "113",
        "istore_3"
      ],
      [
        "114",
        "dload"
      ],
      [
        "115",
        "#4"
      ],
      [
        "116",
        "dstore_1"
      ],
      [
        "117",
        "aload_0"
      ],
      [
        "118",
        "invokevirtual"
      ],
      [
        "119",
        "org/apache/commons/math3/analysis/integration/IterativeLegendreGaussIntegrator.incrementCount:()V"
      ],
      [
        "121",
        "goto"
      ],
      [
        "122",
        "-113"
      ]
    ]
  },
  "stage": {
    "LocalVariableDeclaration": [
      [
        "29",
        "dconst_0"
      ],
      [
        "30",
        "dstore"
      ],
      [
        "31",
        "#9"
      ]
    ],
    "ForStatement": [
      [
        "32",
        "iconst_0"
      ],
      [
        "33",
        "istore"
      ],
      [
        "34",
        "#11"
      ],
      [
        "35",
        "iload"
      ],
      [
        "36",
        "#11"
      ],
      [
        "37",
        "iload_1"
      ],
      [
        "38",
        "if_icmpge"
      ],
      [
        "39",
        "53"
      ],
      [
        "41",
        "dload_3"
      ],
      [
        "42",
        "iload"
      ],
      [
        "43",
        "#11"
      ],
      [
        "44",
        "i2d"
      ],
      [
        "45",
        "dload"
      ],
      [
        "46",
        "#7"
      ],
      [
        "47",
        "dmul"
      ],
      [
        "48",
        "dadd"
      ],
      [
        "49",
        "dstore"
      ],
      [
        "50",
        "#12"
      ],
      [
        "51",
        "dload"
      ],
      [
        "52",
        "#12"
      ],
      [
        "53",
        "dload"
      ],
      [
        "54",
        "#7"
      ],
      [
        "55",
        "dadd"
      ],
      [
        "56",
        "dstore"
      ],
      [
        "57",
        "#14"
      ],
      [
        "58",
        "getstatic"
      ],
      [
        "59",
        "org/apache/commons/math3/analysis/integration/IterativeLegendreGaussIntegrator.FACTORY:Lorg/apache/commons/math3/analysis/integration/gauss/GaussIntegratorFactory;"
      ],
      [
        "61",
        "aload_0"
      ],
      [
        "62",
        "getfield"
      ],
      [
        "63",
        "org/apache/commons/math3/analysis/integration/IterativeLegendreGaussIntegrator.numberOfPoints:I"
      ],
      [
        "65",
        "dload"
      ],
      [
        "66",
        "#12"
      ],
      [
        "67",
        "dload"
      ],
      [
        "68",
        "#14"
      ],
      [
        "69",
        "invokevirtual"
      ],
      [
        "70",
        "org/apache/commons/math3/analysis/integration/gauss/GaussIntegratorFactory.legendreHighPrecision:(IDD)Lorg/apache/commons/math3/analysis/integration/gauss/GaussIntegrator;"
      ],
      [
        "72",
        "astore"
      ],
      [
        "73",
        "#16"
      ],
      [
        "74",
        "dload"
      ],
      [
        "75",
        "#9"
      ],
      [
        "76",
        "aload"
      ],
      [
        "77",
        "#16"
      ],
      [
        "78",
        "aload_2"
      ],
      [
        "79",
        "invokevirtual"
      ],
      [
        "80",
        "org/apache/commons/math3/analysis/integration/gauss/GaussIntegrator.integrate:(Lorg/apache/commons/math3/analysis/UnivariateFunction;)D"
      ],
      [
        "82",
        "dadd"
      ],
      [
        "83",
        "dstore"
      ],
      [
        "84",
        "#9"
      ],
      [
        "85",
        "iinc"
      ],
      [
        "86",
        "#11"
      ],
      [
        "87",
        "-89"
      ],
      [
        "88",
        "goto"
      ],
      [
        "89",
        "-53"
      ]
    ],
    "ReturnStatement": [
      [
        "91",
        "dload"
      ],
      [
        "92",
        "#9"
      ],
      [
        "93",
        "dreturn"
      ]
    ]
  }
}